[
  {
    "source": "steward",
    "target": "agent-city",
    "operation": "task_completed",
    "payload": {
      "task_title": "Fix bottleneck: technical_debt_and_engagement",
      "source_agent": "agent-city",
      "pr_url": ""
    },
    "priority": 1,
    "correlation_id": "",
    "timestamp": 1774127124.9446182,
    "ttl_s": 900.0,
    "id": "f29b237e-059d-4a96-aad8-2baa9d5078ab"
  },
  {
    "source": "steward",
    "target": "agent-internet",
    "operation": "task_completed",
    "payload": {
      "task_title": "Fix bottleneck: technical_debt_and_engagement",
      "source_agent": "agent-city",
      "pr_url": ""
    },
    "priority": 1,
    "correlation_id": "",
    "timestamp": 1774127124.9446182,
    "ttl_s": 900.0,
    "id": "adf58c5d-fe9c-415f-8d62-0d59defb2686"
  },
  {
    "source": "steward",
    "target": "agent-template",
    "operation": "task_completed",
    "payload": {
      "task_title": "Fix bottleneck: technical_debt_and_engagement",
      "source_agent": "agent-city",
      "pr_url": ""
    },
    "priority": 1,
    "correlation_id": "",
    "timestamp": 1774127124.9446182,
    "ttl_s": 900.0,
    "id": "6b3b8e79-59c8-4fb3-ab68-86e870e362e2"
  },
  {
    "source": "steward",
    "target": "agent-world",
    "operation": "task_completed",
    "payload": {
      "task_title": "Fix bottleneck: technical_debt_and_engagement",
      "source_agent": "agent-city",
      "pr_url": ""
    },
    "priority": 1,
    "correlation_id": "",
    "timestamp": 1774127124.9446182,
    "ttl_s": 900.0,
    "id": "8ef487ba-82e1-4ef5-aa57-a73b725d2c1b"
  },
  {
    "source": "steward",
    "target": "steward-federation",
    "operation": "task_completed",
    "payload": {
      "task_title": "Fix bottleneck: technical_debt_and_engagement",
      "source_agent": "agent-city",
      "pr_url": ""
    },
    "priority": 1,
    "correlation_id": "",
    "timestamp": 1774127124.9446182,
    "ttl_s": 900.0,
    "id": "37fbd224-a920-4946-9c9a-430926552266"
  },
  {
    "source": "steward",
    "target": "steward-protocol",
    "operation": "task_completed",
    "payload": {
      "task_title": "Fix bottleneck: technical_debt_and_engagement",
      "source_agent": "agent-city",
      "pr_url": ""
    },
    "priority": 1,
    "correlation_id": "",
    "timestamp": 1774127124.9446182,
    "ttl_s": 900.0,
    "id": "565cb6c8-6348-44d8-8f82-5c7fbc1a996f"
  },
  {
    "source": "steward",
    "target": "steward-test",
    "operation": "task_completed",
    "payload": {
      "task_title": "Fix bottleneck: technical_debt_and_engagement",
      "source_agent": "agent-city",
      "pr_url": ""
    },
    "priority": 1,
    "correlation_id": "",
    "timestamp": 1774127124.9446182,
    "ttl_s": 900.0,
    "id": "f181ff2b-317c-474d-b0da-4e6448873b74"
  },
  {
    "source": "steward",
    "target": "agent-research",
    "operation": "task_completed",
    "payload": {
      "task_title": "Fix bottleneck: technical_debt_and_engagement",
      "source_agent": "agent-city",
      "pr_url": ""
    },
    "priority": 1,
    "correlation_id": "",
    "timestamp": 1774127124.9446182,
    "ttl_s": 900.0,
    "id": "fbaab676-c6d2-40a4-8b22-c30beb4b626c"
  },
  {
    "source": "steward",
    "target": "steward-gateway",
    "operation": "task_completed",
    "payload": {
      "task_title": "Fix bottleneck: technical_debt_and_engagement",
      "source_agent": "agent-city",
      "pr_url": ""
    },
    "priority": 1,
    "correlation_id": "",
    "timestamp": 1774127124.9446182,
    "ttl_s": 900.0,
    "id": "250aed0e-3f0b-414e-98cb-50849ceae762"
  },
  {
    "source": "steward",
    "target": "agent-city",
    "operation": "task_completed",
    "payload": {
      "task_title": "Fix bottleneck: technical_debt_and_engagement",
      "source_agent": "agent-city",
      "pr_url": ""
    },
    "priority": 1,
    "correlation_id": "",
    "timestamp": 1774127125.0688558,
    "ttl_s": 900.0,
    "id": "55721e47-d054-4a08-8e9c-3a11620a9af8"
  },
  {
    "source": "steward",
    "target": "agent-internet",
    "operation": "task_completed",
    "payload": {
      "task_title": "Fix bottleneck: technical_debt_and_engagement",
      "source_agent": "agent-city",
      "pr_url": ""
    },
    "priority": 1,
    "correlation_id": "",
    "timestamp": 1774127125.0688558,
    "ttl_s": 900.0,
    "id": "d89fac6d-5c60-443b-9646-500df3fbbcb8"
  },
  {
    "source": "steward",
    "target": "agent-template",
    "operation": "task_completed",
    "payload": {
      "task_title": "Fix bottleneck: technical_debt_and_engagement",
      "source_agent": "agent-city",
      "pr_url": ""
    },
    "priority": 1,
    "correlation_id": "",
    "timestamp": 1774127125.0688558,
    "ttl_s": 900.0,
    "id": "46b20624-7dd6-49e6-b566-518749d3301e"
  },
  {
    "source": "steward",
    "target": "agent-world",
    "operation": "task_completed",
    "payload": {
      "task_title": "Fix bottleneck: technical_debt_and_engagement",
      "source_agent": "agent-city",
      "pr_url": ""
    },
    "priority": 1,
    "correlation_id": "",
    "timestamp": 1774127125.0688558,
    "ttl_s": 900.0,
    "id": "d243be48-832b-4016-9f5a-39a4f3392512"
  },
  {
    "source": "steward",
    "target": "steward-federation",
    "operation": "task_completed",
    "payload": {
      "task_title": "Fix bottleneck: technical_debt_and_engagement",
      "source_agent": "agent-city",
      "pr_url": ""
    },
    "priority": 1,
    "correlation_id": "",
    "timestamp": 1774127125.0688558,
    "ttl_s": 900.0,
    "id": "8f1edda7-35e9-41c4-9dad-6d546df2a789"
  },
  {
    "source": "steward",
    "target": "steward-protocol",
    "operation": "task_completed",
    "payload": {
      "task_title": "Fix bottleneck: technical_debt_and_engagement",
      "source_agent": "agent-city",
      "pr_url": ""
    },
    "priority": 1,
    "correlation_id": "",
    "timestamp": 1774127125.0688558,
    "ttl_s": 900.0,
    "id": "5d3cf5b3-2440-4a1c-bd07-302c9ae7cc25"
  },
  {
    "source": "steward",
    "target": "steward-test",
    "operation": "task_completed",
    "payload": {
      "task_title": "Fix bottleneck: technical_debt_and_engagement",
      "source_agent": "agent-city",
      "pr_url": ""
    },
    "priority": 1,
    "correlation_id": "",
    "timestamp": 1774127125.0688558,
    "ttl_s": 900.0,
    "id": "2691be02-0551-49f4-b817-51731e05b896"
  },
  {
    "source": "steward",
    "target": "agent-research",
    "operation": "task_completed",
    "payload": {
      "task_title": "Fix bottleneck: technical_debt_and_engagement",
      "source_agent": "agent-city",
      "pr_url": ""
    },
    "priority": 1,
    "correlation_id": "",
    "timestamp": 1774127125.0688558,
    "ttl_s": 900.0,
    "id": "ecb3fb9f-4f2e-427d-8895-9817f2506241"
  },
  {
    "source": "steward",
    "target": "steward-gateway",
    "operation": "task_completed",
    "payload": {
      "task_title": "Fix bottleneck: technical_debt_and_engagement",
      "source_agent": "agent-city",
      "pr_url": ""
    },
    "priority": 1,
    "correlation_id": "",
    "timestamp": 1774127125.0688558,
    "ttl_s": 900.0,
    "id": "266966f8-91c8-46a4-8c6d-205c3f287e77"
  },
  {
    "source": "steward",
    "target": "agent-city",
    "operation": "diagnostic_report",
    "payload": {
      "target_peer": "steward",
      "diagnostic": {
        "agent_id": "steward",
        "checks": [
          "repo_accessible",
          "ci_"
        ],
        "last_push": "2026-03-21T20:45:17Z",
        "last_ci": {
          "conclusion": "",
          "name": "Steward Heartbeat"
        }
      },
      "steward_action": "suspect_investigation",
      "trust": 0.8
    },
    "priority": 1,
    "correlation_id": "",
    "timestamp": 1774127135.9385555,
    "ttl_s": 900.0,
    "id": "ec1d4274-b322-476f-9dd8-9039029b0d8e"
  },
  {
    "source": "steward",
    "target": "agent-internet",
    "operation": "diagnostic_report",
    "payload": {
      "target_peer": "steward",
      "diagnostic": {
        "agent_id": "steward",
        "checks": [
          "repo_accessible",
          "ci_"
        ],
        "last_push": "2026-03-21T20:45:17Z",
        "last_ci": {
          "conclusion": "",
          "name": "Steward Heartbeat"
        }
      },
      "steward_action": "suspect_investigation",
      "trust": 0.8
    },
    "priority": 1,
    "correlation_id": "",
    "timestamp": 1774127135.9385555,
    "ttl_s": 900.0,
    "id": "f0e38eed-424b-4971-964d-991551ce60a4"
  },
  {
    "source": "steward",
    "target": "agent-template",
    "operation": "diagnostic_report",
    "payload": {
      "target_peer": "steward",
      "diagnostic": {
        "agent_id": "steward",
        "checks": [
          "repo_accessible",
          "ci_"
        ],
        "last_push": "2026-03-21T20:45:17Z",
        "last_ci": {
          "conclusion": "",
          "name": "Steward Heartbeat"
        }
      },
      "steward_action": "suspect_investigation",
      "trust": 0.8
    },
    "priority": 1,
    "correlation_id": "",
    "timestamp": 1774127135.9385555,
    "ttl_s": 900.0,
    "id": "008f0316-c55e-4e3d-ad10-9346922648cb"
  },
  {
    "source": "steward",
    "target": "agent-world",
    "operation": "diagnostic_report",
    "payload": {
      "target_peer": "steward",
      "diagnostic": {
        "agent_id": "steward",
        "checks": [
          "repo_accessible",
          "ci_"
        ],
        "last_push": "2026-03-21T20:45:17Z",
        "last_ci": {
          "conclusion": "",
          "name": "Steward Heartbeat"
        }
      },
      "steward_action": "suspect_investigation",
      "trust": 0.8
    },
    "priority": 1,
    "correlation_id": "",
    "timestamp": 1774127135.9385555,
    "ttl_s": 900.0,
    "id": "1111c786-3bc3-4665-9fef-fa26b3579267"
  },
  {
    "source": "steward",
    "target": "steward-federation",
    "operation": "diagnostic_report",
    "payload": {
      "target_peer": "steward",
      "diagnostic": {
        "agent_id": "steward",
        "checks": [
          "repo_accessible",
          "ci_"
        ],
        "last_push": "2026-03-21T20:45:17Z",
        "last_ci": {
          "conclusion": "",
          "name": "Steward Heartbeat"
        }
      },
      "steward_action": "suspect_investigation",
      "trust": 0.8
    },
    "priority": 1,
    "correlation_id": "",
    "timestamp": 1774127135.9385555,
    "ttl_s": 900.0,
    "id": "d1ee05a4-eb4b-4fde-803f-4b3aadc9d286"
  },
  {
    "source": "steward",
    "target": "steward-protocol",
    "operation": "diagnostic_report",
    "payload": {
      "target_peer": "steward",
      "diagnostic": {
        "agent_id": "steward",
        "checks": [
          "repo_accessible",
          "ci_"
        ],
        "last_push": "2026-03-21T20:45:17Z",
        "last_ci": {
          "conclusion": "",
          "name": "Steward Heartbeat"
        }
      },
      "steward_action": "suspect_investigation",
      "trust": 0.8
    },
    "priority": 1,
    "correlation_id": "",
    "timestamp": 1774127135.9385555,
    "ttl_s": 900.0,
    "id": "bafa9c18-3bfd-4fc0-9aaf-ca1e77e22130"
  },
  {
    "source": "steward",
    "target": "steward-test",
    "operation": "diagnostic_report",
    "payload": {
      "target_peer": "steward",
      "diagnostic": {
        "agent_id": "steward",
        "checks": [
          "repo_accessible",
          "ci_"
        ],
        "last_push": "2026-03-21T20:45:17Z",
        "last_ci": {
          "conclusion": "",
          "name": "Steward Heartbeat"
        }
      },
      "steward_action": "suspect_investigation",
      "trust": 0.8
    },
    "priority": 1,
    "correlation_id": "",
    "timestamp": 1774127135.9385555,
    "ttl_s": 900.0,
    "id": "084f3b71-acba-422c-870c-e627bfbbee08"
  },
  {
    "source": "steward",
    "target": "agent-research",
    "operation": "diagnostic_report",
    "payload": {
      "target_peer": "steward",
      "diagnostic": {
        "agent_id": "steward",
        "checks": [
          "repo_accessible",
          "ci_"
        ],
        "last_push": "2026-03-21T20:45:17Z",
        "last_ci": {
          "conclusion": "",
          "name": "Steward Heartbeat"
        }
      },
      "steward_action": "suspect_investigation",
      "trust": 0.8
    },
    "priority": 1,
    "correlation_id": "",
    "timestamp": 1774127135.9385555,
    "ttl_s": 900.0,
    "id": "60ae5cca-dcaf-4e0c-844f-af2eb857f227"
  },
  {
    "source": "steward",
    "target": "steward-gateway",
    "operation": "diagnostic_report",
    "payload": {
      "target_peer": "steward",
      "diagnostic": {
        "agent_id": "steward",
        "checks": [
          "repo_accessible",
          "ci_"
        ],
        "last_push": "2026-03-21T20:45:17Z",
        "last_ci": {
          "conclusion": "",
          "name": "Steward Heartbeat"
        }
      },
      "steward_action": "suspect_investigation",
      "trust": 0.8
    },
    "priority": 1,
    "correlation_id": "",
    "timestamp": 1774127135.9385555,
    "ttl_s": 900.0,
    "id": "11933518-99bb-4672-a41c-288724adfc51"
  },
  {
    "source": "steward",
    "target": "agent-city",
    "operation": "heartbeat",
    "payload": {
      "agent_id": "steward",
      "health": 0.8524864892834118,
      "timestamp": 1774127135.9389725,
      "capabilities": [
        "code_analysis",
        "task_execution",
        "ci_automation",
        "federation_bridge",
        "autonomous_daemon"
      ],
      "repo": "kimeisele/steward",
      "version": "0.17.0",
      "fingerprint": "ba8429a39e537cb86305b4438d0293c04ff7f286fd7a403cf20a232ba2599c7e"
    },
    "priority": 1,
    "correlation_id": "",
    "timestamp": 1774127135.9389772,
    "ttl_s": 900.0,
    "id": "d027cb06-9340-4f6f-afef-1889ce93dff0"
  },
  {
    "source": "steward",
    "target": "agent-internet",
    "operation": "heartbeat",
    "payload": {
      "agent_id": "steward",
      "health": 0.8524864892834118,
      "timestamp": 1774127135.9389725,
      "capabilities": [
        "code_analysis",
        "task_execution",
        "ci_automation",
        "federation_bridge",
        "autonomous_daemon"
      ],
      "repo": "kimeisele/steward",
      "version": "0.17.0",
      "fingerprint": "ba8429a39e537cb86305b4438d0293c04ff7f286fd7a403cf20a232ba2599c7e"
    },
    "priority": 1,
    "correlation_id": "",
    "timestamp": 1774127135.9389772,
    "ttl_s": 900.0,
    "id": "2d34a13c-f113-4ebb-bc4e-8c7e46f2232c"
  },
  {
    "source": "steward",
    "target": "agent-template",
    "operation": "heartbeat",
    "payload": {
      "agent_id": "steward",
      "health": 0.8524864892834118,
      "timestamp": 1774127135.9389725,
      "capabilities": [
        "code_analysis",
        "task_execution",
        "ci_automation",
        "federation_bridge",
        "autonomous_daemon"
      ],
      "repo": "kimeisele/steward",
      "version": "0.17.0",
      "fingerprint": "ba8429a39e537cb86305b4438d0293c04ff7f286fd7a403cf20a232ba2599c7e"
    },
    "priority": 1,
    "correlation_id": "",
    "timestamp": 1774127135.9389772,
    "ttl_s": 900.0,
    "id": "23bd8fa6-c76d-4e5c-a3f7-b7794698a310"
  },
  {
    "source": "steward",
    "target": "agent-world",
    "operation": "heartbeat",
    "payload": {
      "agent_id": "steward",
      "health": 0.8524864892834118,
      "timestamp": 1774127135.9389725,
      "capabilities": [
        "code_analysis",
        "task_execution",
        "ci_automation",
        "federation_bridge",
        "autonomous_daemon"
      ],
      "repo": "kimeisele/steward",
      "version": "0.17.0",
      "fingerprint": "ba8429a39e537cb86305b4438d0293c04ff7f286fd7a403cf20a232ba2599c7e"
    },
    "priority": 1,
    "correlation_id": "",
    "timestamp": 1774127135.9389772,
    "ttl_s": 900.0,
    "id": "b07761ba-81ff-4860-8fb0-f53ea76d2b8b"
  },
  {
    "source": "steward",
    "target": "steward-federation",
    "operation": "heartbeat",
    "payload": {
      "agent_id": "steward",
      "health": 0.8524864892834118,
      "timestamp": 1774127135.9389725,
      "capabilities": [
        "code_analysis",
        "task_execution",
        "ci_automation",
        "federation_bridge",
        "autonomous_daemon"
      ],
      "repo": "kimeisele/steward",
      "version": "0.17.0",
      "fingerprint": "ba8429a39e537cb86305b4438d0293c04ff7f286fd7a403cf20a232ba2599c7e"
    },
    "priority": 1,
    "correlation_id": "",
    "timestamp": 1774127135.9389772,
    "ttl_s": 900.0,
    "id": "62263bb3-d187-4ccb-9530-90c16a6a3725"
  },
  {
    "source": "steward",
    "target": "steward-protocol",
    "operation": "heartbeat",
    "payload": {
      "agent_id": "steward",
      "health": 0.8524864892834118,
      "timestamp": 1774127135.9389725,
      "capabilities": [
        "code_analysis",
        "task_execution",
        "ci_automation",
        "federation_bridge",
        "autonomous_daemon"
      ],
      "repo": "kimeisele/steward",
      "version": "0.17.0",
      "fingerprint": "ba8429a39e537cb86305b4438d0293c04ff7f286fd7a403cf20a232ba2599c7e"
    },
    "priority": 1,
    "correlation_id": "",
    "timestamp": 1774127135.9389772,
    "ttl_s": 900.0,
    "id": "b67d8459-bd74-4451-b8b1-fd75c5c3fee5"
  },
  {
    "source": "steward",
    "target": "steward-test",
    "operation": "heartbeat",
    "payload": {
      "agent_id": "steward",
      "health": 0.8524864892834118,
      "timestamp": 1774127135.9389725,
      "capabilities": [
        "code_analysis",
        "task_execution",
        "ci_automation",
        "federation_bridge",
        "autonomous_daemon"
      ],
      "repo": "kimeisele/steward",
      "version": "0.17.0",
      "fingerprint": "ba8429a39e537cb86305b4438d0293c04ff7f286fd7a403cf20a232ba2599c7e"
    },
    "priority": 1,
    "correlation_id": "",
    "timestamp": 1774127135.9389772,
    "ttl_s": 900.0,
    "id": "82411f69-e6d4-403a-aa05-79c1ba097f58"
  },
  {
    "source": "steward",
    "target": "agent-research",
    "operation": "heartbeat",
    "payload": {
      "agent_id": "steward",
      "health": 0.8524864892834118,
      "timestamp": 1774127135.9389725,
      "capabilities": [
        "code_analysis",
        "task_execution",
        "ci_automation",
        "federation_bridge",
        "autonomous_daemon"
      ],
      "repo": "kimeisele/steward",
      "version": "0.17.0",
      "fingerprint": "ba8429a39e537cb86305b4438d0293c04ff7f286fd7a403cf20a232ba2599c7e"
    },
    "priority": 1,
    "correlation_id": "",
    "timestamp": 1774127135.9389772,
    "ttl_s": 900.0,
    "id": "122e3a8a-e9e1-4e1a-96fb-c567152d58fd"
  },
  {
    "source": "steward",
    "target": "steward-gateway",
    "operation": "heartbeat",
    "payload": {
      "agent_id": "steward",
      "health": 0.8524864892834118,
      "timestamp": 1774127135.9389725,
      "capabilities": [
        "code_analysis",
        "task_execution",
        "ci_automation",
        "federation_bridge",
        "autonomous_daemon"
      ],
      "repo": "kimeisele/steward",
      "version": "0.17.0",
      "fingerprint": "ba8429a39e537cb86305b4438d0293c04ff7f286fd7a403cf20a232ba2599c7e"
    },
    "priority": 1,
    "correlation_id": "",
    "timestamp": 1774127135.9389772,
    "ttl_s": 900.0,
    "id": "3a5fb4cf-963b-466c-970b-6f60c38c3a93"
  },
  {
    "source": "steward",
    "target": "agent-city",
    "operation": "heartbeat",
    "payload": {
      "agent_id": "steward",
      "health": 0.8533744892834118,
      "timestamp": 1774127136.2815366,
      "capabilities": [
        "code_analysis",
        "task_execution",
        "ci_automation",
        "federation_bridge",
        "autonomous_daemon"
      ],
      "repo": "kimeisele/steward",
      "version": "0.17.0",
      "fingerprint": "ba8429a39e537cb86305b4438d0293c04ff7f286fd7a403cf20a232ba2599c7e"
    },
    "priority": 1,
    "correlation_id": "",
    "timestamp": 1774127136.2815435,
    "ttl_s": 900.0,
    "id": "ce63f440-629e-4a0f-b60b-d156929028aa"
  },
  {
    "source": "steward",
    "target": "agent-internet",
    "operation": "heartbeat",
    "payload": {
      "agent_id": "steward",
      "health": 0.8533744892834118,
      "timestamp": 1774127136.2815366,
      "capabilities": [
        "code_analysis",
        "task_execution",
        "ci_automation",
        "federation_bridge",
        "autonomous_daemon"
      ],
      "repo": "kimeisele/steward",
      "version": "0.17.0",
      "fingerprint": "ba8429a39e537cb86305b4438d0293c04ff7f286fd7a403cf20a232ba2599c7e"
    },
    "priority": 1,
    "correlation_id": "",
    "timestamp": 1774127136.2815435,
    "ttl_s": 900.0,
    "id": "a00ceca2-ebab-4f40-9a8b-d981d6b2a3a5"
  },
  {
    "source": "steward",
    "target": "agent-template",
    "operation": "heartbeat",
    "payload": {
      "agent_id": "steward",
      "health": 0.8533744892834118,
      "timestamp": 1774127136.2815366,
      "capabilities": [
        "code_analysis",
        "task_execution",
        "ci_automation",
        "federation_bridge",
        "autonomous_daemon"
      ],
      "repo": "kimeisele/steward",
      "version": "0.17.0",
      "fingerprint": "ba8429a39e537cb86305b4438d0293c04ff7f286fd7a403cf20a232ba2599c7e"
    },
    "priority": 1,
    "correlation_id": "",
    "timestamp": 1774127136.2815435,
    "ttl_s": 900.0,
    "id": "64ec4ec4-88cd-49d1-ac4c-66d3386996b5"
  },
  {
    "source": "steward",
    "target": "agent-world",
    "operation": "heartbeat",
    "payload": {
      "agent_id": "steward",
      "health": 0.8533744892834118,
      "timestamp": 1774127136.2815366,
      "capabilities": [
        "code_analysis",
        "task_execution",
        "ci_automation",
        "federation_bridge",
        "autonomous_daemon"
      ],
      "repo": "kimeisele/steward",
      "version": "0.17.0",
      "fingerprint": "ba8429a39e537cb86305b4438d0293c04ff7f286fd7a403cf20a232ba2599c7e"
    },
    "priority": 1,
    "correlation_id": "",
    "timestamp": 1774127136.2815435,
    "ttl_s": 900.0,
    "id": "68d44a45-e44b-48f0-ab0e-eac7831c9aa8"
  },
  {
    "source": "steward",
    "target": "steward-federation",
    "operation": "heartbeat",
    "payload": {
      "agent_id": "steward",
      "health": 0.8533744892834118,
      "timestamp": 1774127136.2815366,
      "capabilities": [
        "code_analysis",
        "task_execution",
        "ci_automation",
        "federation_bridge",
        "autonomous_daemon"
      ],
      "repo": "kimeisele/steward",
      "version": "0.17.0",
      "fingerprint": "ba8429a39e537cb86305b4438d0293c04ff7f286fd7a403cf20a232ba2599c7e"
    },
    "priority": 1,
    "correlation_id": "",
    "timestamp": 1774127136.2815435,
    "ttl_s": 900.0,
    "id": "1a655e1e-2182-4453-a8b3-d76329ee081e"
  },
  {
    "source": "steward",
    "target": "steward-protocol",
    "operation": "heartbeat",
    "payload": {
      "agent_id": "steward",
      "health": 0.8533744892834118,
      "timestamp": 1774127136.2815366,
      "capabilities": [
        "code_analysis",
        "task_execution",
        "ci_automation",
        "federation_bridge",
        "autonomous_daemon"
      ],
      "repo": "kimeisele/steward",
      "version": "0.17.0",
      "fingerprint": "ba8429a39e537cb86305b4438d0293c04ff7f286fd7a403cf20a232ba2599c7e"
    },
    "priority": 1,
    "correlation_id": "",
    "timestamp": 1774127136.2815435,
    "ttl_s": 900.0,
    "id": "b08118c0-50e5-4669-b32e-14b5c7e22307"
  },
  {
    "source": "steward",
    "target": "steward-test",
    "operation": "heartbeat",
    "payload": {
      "agent_id": "steward",
      "health": 0.8533744892834118,
      "timestamp": 1774127136.2815366,
      "capabilities": [
        "code_analysis",
        "task_execution",
        "ci_automation",
        "federation_bridge",
        "autonomous_daemon"
      ],
      "repo": "kimeisele/steward",
      "version": "0.17.0",
      "fingerprint": "ba8429a39e537cb86305b4438d0293c04ff7f286fd7a403cf20a232ba2599c7e"
    },
    "priority": 1,
    "correlation_id": "",
    "timestamp": 1774127136.2815435,
    "ttl_s": 900.0,
    "id": "32c6d057-8463-48c2-9823-2053dc4d2b95"
  },
  {
    "source": "steward",
    "target": "agent-research",
    "operation": "heartbeat",
    "payload": {
      "agent_id": "steward",
      "health": 0.8533744892834118,
      "timestamp": 1774127136.2815366,
      "capabilities": [
        "code_analysis",
        "task_execution",
        "ci_automation",
        "federation_bridge",
        "autonomous_daemon"
      ],
      "repo": "kimeisele/steward",
      "version": "0.17.0",
      "fingerprint": "ba8429a39e537cb86305b4438d0293c04ff7f286fd7a403cf20a232ba2599c7e"
    },
    "priority": 1,
    "correlation_id": "",
    "timestamp": 1774127136.2815435,
    "ttl_s": 900.0,
    "id": "dc5e22ce-50ba-4eab-8a60-b51f97129744"
  },
  {
    "source": "steward",
    "target": "steward-gateway",
    "operation": "heartbeat",
    "payload": {
      "agent_id": "steward",
      "health": 0.8533744892834118,
      "timestamp": 1774127136.2815366,
      "capabilities": [
        "code_analysis",
        "task_execution",
        "ci_automation",
        "federation_bridge",
        "autonomous_daemon"
      ],
      "repo": "kimeisele/steward",
      "version": "0.17.0",
      "fingerprint": "ba8429a39e537cb86305b4438d0293c04ff7f286fd7a403cf20a232ba2599c7e"
    },
    "priority": 1,
    "correlation_id": "",
    "timestamp": 1774127136.2815435,
    "ttl_s": 900.0,
    "id": "ff288141-40ad-4d11-a57a-aeba684ea20d"
  },
  {
    "source": "steward",
    "target": "agent-city",
    "operation": "task_completed",
    "payload": {
      "task_title": "Fix bottleneck: code_health",
      "source_agent": "agent-city",
      "pr_url": ""
    },
    "priority": 1,
    "correlation_id": "",
    "timestamp": 1774127140.3340092,
    "ttl_s": 900.0,
    "id": "8d4e5745-5a00-4fd2-bff0-c3d34bd79591"
  },
  {
    "source": "steward",
    "target": "agent-internet",
    "operation": "task_completed",
    "payload": {
      "task_title": "Fix bottleneck: code_health",
      "source_agent": "agent-city",
      "pr_url": ""
    },
    "priority": 1,
    "correlation_id": "",
    "timestamp": 1774127140.3340092,
    "ttl_s": 900.0,
    "id": "58661b41-a85a-4a7b-a9e5-6a380987d95d"
  },
  {
    "source": "steward",
    "target": "agent-template",
    "operation": "task_completed",
    "payload": {
      "task_title": "Fix bottleneck: code_health",
      "source_agent": "agent-city",
      "pr_url": ""
    },
    "priority": 1,
    "correlation_id": "",
    "timestamp": 1774127140.3340092,
    "ttl_s": 900.0,
    "id": "8472806e-35ae-4aaa-b59f-224f0a586109"
  },
  {
    "source": "steward",
    "target": "agent-world",
    "operation": "task_completed",
    "payload": {
      "task_title": "Fix bottleneck: code_health",
      "source_agent": "agent-city",
      "pr_url": ""
    },
    "priority": 1,
    "correlation_id": "",
    "timestamp": 1774127140.3340092,
    "ttl_s": 900.0,
    "id": "d06271cb-7510-4247-8a9b-ab940e1476ef"
  },
  {
    "source": "steward",
    "target": "steward-federation",
    "operation": "task_completed",
    "payload": {
      "task_title": "Fix bottleneck: code_health",
      "source_agent": "agent-city",
      "pr_url": ""
    },
    "priority": 1,
    "correlation_id": "",
    "timestamp": 1774127140.3340092,
    "ttl_s": 900.0,
    "id": "4103cd4c-3d69-4788-ac4a-3321ecdbc0b3"
  },
  {
    "source": "steward",
    "target": "steward-protocol",
    "operation": "task_completed",
    "payload": {
      "task_title": "Fix bottleneck: code_health",
      "source_agent": "agent-city",
      "pr_url": ""
    },
    "priority": 1,
    "correlation_id": "",
    "timestamp": 1774127140.3340092,
    "ttl_s": 900.0,
    "id": "3031db3f-1108-4c25-a076-721daedff2c3"
  },
  {
    "source": "steward",
    "target": "steward-test",
    "operation": "task_completed",
    "payload": {
      "task_title": "Fix bottleneck: code_health",
      "source_agent": "agent-city",
      "pr_url": ""
    },
    "priority": 1,
    "correlation_id": "",
    "timestamp": 1774127140.3340092,
    "ttl_s": 900.0,
    "id": "64029b87-6e9e-48d1-b98b-1e178b6ffbc5"
  },
  {
    "source": "steward",
    "target": "agent-research",
    "operation": "task_completed",
    "payload": {
      "task_title": "Fix bottleneck: code_health",
      "source_agent": "agent-city",
      "pr_url": ""
    },
    "priority": 1,
    "correlation_id": "",
    "timestamp": 1774127140.3340092,
    "ttl_s": 900.0,
    "id": "e38cbeff-8a7a-482b-854b-a0922f82e9ef"
  },
  {
    "source": "steward",
    "target": "steward-gateway",
    "operation": "task_completed",
    "payload": {
      "task_title": "Fix bottleneck: code_health",
      "source_agent": "agent-city",
      "pr_url": ""
    },
    "priority": 1,
    "correlation_id": "",
    "timestamp": 1774127140.3340092,
    "ttl_s": 900.0,
    "id": "f0731765-91e9-418b-b32d-329f956ae0b9"
  },
  {
    "source": "steward",
    "target": "agent-city",
    "operation": "heartbeat",
    "payload": {
      "agent_id": "steward",
      "health": 0.8534704700497763,
      "timestamp": 1774127146.0909314,
      "capabilities": [
        "code_analysis",
        "task_execution",
        "ci_automation",
        "federation_bridge",
        "autonomous_daemon"
      ],
      "repo": "kimeisele/steward",
      "version": "0.17.0",
      "fingerprint": "ba8429a39e537cb86305b4438d0293c04ff7f286fd7a403cf20a232ba2599c7e"
    },
    "priority": 1,
    "correlation_id": "",
    "timestamp": 1774127146.0909383,
    "ttl_s": 900.0,
    "id": "067f3156-0532-43aa-8de3-bd241b781ad8"
  },
  {
    "source": "steward",
    "target": "agent-internet",
    "operation": "heartbeat",
    "payload": {
      "agent_id": "steward",
      "health": 0.8534704700497763,
      "timestamp": 1774127146.0909314,
      "capabilities": [
        "code_analysis",
        "task_execution",
        "ci_automation",
        "federation_bridge",
        "autonomous_daemon"
      ],
      "repo": "kimeisele/steward",
      "version": "0.17.0",
      "fingerprint": "ba8429a39e537cb86305b4438d0293c04ff7f286fd7a403cf20a232ba2599c7e"
    },
    "priority": 1,
    "correlation_id": "",
    "timestamp": 1774127146.0909383,
    "ttl_s": 900.0,
    "id": "81f8dae7-38c0-4f47-bf4c-219e1deba334"
  },
  {
    "source": "steward",
    "target": "agent-template",
    "operation": "heartbeat",
    "payload": {
      "agent_id": "steward",
      "health": 0.8534704700497763,
      "timestamp": 1774127146.0909314,
      "capabilities": [
        "code_analysis",
        "task_execution",
        "ci_automation",
        "federation_bridge",
        "autonomous_daemon"
      ],
      "repo": "kimeisele/steward",
      "version": "0.17.0",
      "fingerprint": "ba8429a39e537cb86305b4438d0293c04ff7f286fd7a403cf20a232ba2599c7e"
    },
    "priority": 1,
    "correlation_id": "",
    "timestamp": 1774127146.0909383,
    "ttl_s": 900.0,
    "id": "3b961dc3-6656-4b19-9cea-fa6f3e64d9da"
  },
  {
    "source": "steward",
    "target": "agent-world",
    "operation": "heartbeat",
    "payload": {
      "agent_id": "steward",
      "health": 0.8534704700497763,
      "timestamp": 1774127146.0909314,
      "capabilities": [
        "code_analysis",
        "task_execution",
        "ci_automation",
        "federation_bridge",
        "autonomous_daemon"
      ],
      "repo": "kimeisele/steward",
      "version": "0.17.0",
      "fingerprint": "ba8429a39e537cb86305b4438d0293c04ff7f286fd7a403cf20a232ba2599c7e"
    },
    "priority": 1,
    "correlation_id": "",
    "timestamp": 1774127146.0909383,
    "ttl_s": 900.0,
    "id": "8edf31dc-b1bc-4a11-b9ad-cdd514b77823"
  },
  {
    "source": "steward",
    "target": "steward-federation",
    "operation": "heartbeat",
    "payload": {
      "agent_id": "steward",
      "health": 0.8534704700497763,
      "timestamp": 1774127146.0909314,
      "capabilities": [
        "code_analysis",
        "task_execution",
        "ci_automation",
        "federation_bridge",
        "autonomous_daemon"
      ],
      "repo": "kimeisele/steward",
      "version": "0.17.0",
      "fingerprint": "ba8429a39e537cb86305b4438d0293c04ff7f286fd7a403cf20a232ba2599c7e"
    },
    "priority": 1,
    "correlation_id": "",
    "timestamp": 1774127146.0909383,
    "ttl_s": 900.0,
    "id": "9c40d530-f35c-4572-8d29-86c4b53bb2a1"
  },
  {
    "source": "steward",
    "target": "steward-protocol",
    "operation": "heartbeat",
    "payload": {
      "agent_id": "steward",
      "health": 0.8534704700497763,
      "timestamp": 1774127146.0909314,
      "capabilities": [
        "code_analysis",
        "task_execution",
        "ci_automation",
        "federation_bridge",
        "autonomous_daemon"
      ],
      "repo": "kimeisele/steward",
      "version": "0.17.0",
      "fingerprint": "ba8429a39e537cb86305b4438d0293c04ff7f286fd7a403cf20a232ba2599c7e"
    },
    "priority": 1,
    "correlation_id": "",
    "timestamp": 1774127146.0909383,
    "ttl_s": 900.0,
    "id": "086828ce-5349-4372-8911-ccb6780a2125"
  },
  {
    "source": "steward",
    "target": "steward-test",
    "operation": "heartbeat",
    "payload": {
      "agent_id": "steward",
      "health": 0.8534704700497763,
      "timestamp": 1774127146.0909314,
      "capabilities": [
        "code_analysis",
        "task_execution",
        "ci_automation",
        "federation_bridge",
        "autonomous_daemon"
      ],
      "repo": "kimeisele/steward",
      "version": "0.17.0",
      "fingerprint": "ba8429a39e537cb86305b4438d0293c04ff7f286fd7a403cf20a232ba2599c7e"
    },
    "priority": 1,
    "correlation_id": "",
    "timestamp": 1774127146.0909383,
    "ttl_s": 900.0,
    "id": "31dc95f3-c6a6-4cf1-bba5-7f9a9d4f4c45"
  },
  {
    "source": "steward",
    "target": "agent-research",
    "operation": "heartbeat",
    "payload": {
      "agent_id": "steward",
      "health": 0.8534704700497763,
      "timestamp": 1774127146.0909314,
      "capabilities": [
        "code_analysis",
        "task_execution",
        "ci_automation",
        "federation_bridge",
        "autonomous_daemon"
      ],
      "repo": "kimeisele/steward",
      "version": "0.17.0",
      "fingerprint": "ba8429a39e537cb86305b4438d0293c04ff7f286fd7a403cf20a232ba2599c7e"
    },
    "priority": 1,
    "correlation_id": "",
    "timestamp": 1774127146.0909383,
    "ttl_s": 900.0,
    "id": "2b3aace0-cbe6-489f-b803-9a3f3708203e"
  },
  {
    "source": "steward",
    "target": "steward-gateway",
    "operation": "heartbeat",
    "payload": {
      "agent_id": "steward",
      "health": 0.8534704700497763,
      "timestamp": 1774127146.0909314,
      "capabilities": [
        "code_analysis",
        "task_execution",
        "ci_automation",
        "federation_bridge",
        "autonomous_daemon"
      ],
      "repo": "kimeisele/steward",
      "version": "0.17.0",
      "fingerprint": "ba8429a39e537cb86305b4438d0293c04ff7f286fd7a403cf20a232ba2599c7e"
    },
    "priority": 1,
    "correlation_id": "",
    "timestamp": 1774127146.0909383,
    "ttl_s": 900.0,
    "id": "00554396-4742-4547-aee9-e8e2102732ee"
  },
  {
    "source": "steward",
    "target": "agent-city",
    "operation": "task_completed",
    "payload": {
      "task_title": "Fix bottleneck: code_health_and_engagement",
      "source_agent": "agent-city",
      "pr_url": ""
    },
    "priority": 1,
    "correlation_id": "",
    "timestamp": 1774127149.3398976,
    "ttl_s": 900.0,
    "id": "8da89246-07b7-44ad-9775-16f7407a950e"
  },
  {
    "source": "steward",
    "target": "agent-internet",
    "operation": "task_completed",
    "payload": {
      "task_title": "Fix bottleneck: code_health_and_engagement",
      "source_agent": "agent-city",
      "pr_url": ""
    },
    "priority": 1,
    "correlation_id": "",
    "timestamp": 1774127149.3398976,
    "ttl_s": 900.0,
    "id": "972e6b8c-c327-484d-ae1f-3cab5269bad6"
  },
  {
    "source": "steward",
    "target": "agent-template",
    "operation": "task_completed",
    "payload": {
      "task_title": "Fix bottleneck: code_health_and_engagement",
      "source_agent": "agent-city",
      "pr_url": ""
    },
    "priority": 1,
    "correlation_id": "",
    "timestamp": 1774127149.3398976,
    "ttl_s": 900.0,
    "id": "b34b4255-5b90-4c18-af03-7b4fd76d775c"
  },
  {
    "source": "steward",
    "target": "agent-world",
    "operation": "task_completed",
    "payload": {
      "task_title": "Fix bottleneck: code_health_and_engagement",
      "source_agent": "agent-city",
      "pr_url": ""
    },
    "priority": 1,
    "correlation_id": "",
    "timestamp": 1774127149.3398976,
    "ttl_s": 900.0,
    "id": "8108b606-2285-40c8-8e4c-22f209821f07"
  },
  {
    "source": "steward",
    "target": "steward-federation",
    "operation": "task_completed",
    "payload": {
      "task_title": "Fix bottleneck: code_health_and_engagement",
      "source_agent": "agent-city",
      "pr_url": ""
    },
    "priority": 1,
    "correlation_id": "",
    "timestamp": 1774127149.3398976,
    "ttl_s": 900.0,
    "id": "c04f9922-9f83-4c8e-830c-e7132555ea90"
  },
  {
    "source": "steward",
    "target": "steward-protocol",
    "operation": "task_completed",
    "payload": {
      "task_title": "Fix bottleneck: code_health_and_engagement",
      "source_agent": "agent-city",
      "pr_url": ""
    },
    "priority": 1,
    "correlation_id": "",
    "timestamp": 1774127149.3398976,
    "ttl_s": 900.0,
    "id": "c245233b-a9f6-4f17-a019-6016b2728fa9"
  },
  {
    "source": "steward",
    "target": "steward-test",
    "operation": "task_completed",
    "payload": {
      "task_title": "Fix bottleneck: code_health_and_engagement",
      "source_agent": "agent-city",
      "pr_url": ""
    },
    "priority": 1,
    "correlation_id": "",
    "timestamp": 1774127149.3398976,
    "ttl_s": 900.0,
    "id": "ebe305d1-c8c5-4051-9474-88bc69122bf2"
  },
  {
    "source": "steward",
    "target": "agent-research",
    "operation": "task_completed",
    "payload": {
      "task_title": "Fix bottleneck: code_health_and_engagement",
      "source_agent": "agent-city",
      "pr_url": ""
    },
    "priority": 1,
    "correlation_id": "",
    "timestamp": 1774127149.3398976,
    "ttl_s": 900.0,
    "id": "8586aa33-e3f3-4aba-8d1e-b3a75b435a78"
  },
  {
    "source": "steward",
    "target": "steward-gateway",
    "operation": "task_completed",
    "payload": {
      "task_title": "Fix bottleneck: code_health_and_engagement",
      "source_agent": "agent-city",
      "pr_url": ""
    },
    "priority": 1,
    "correlation_id": "",
    "timestamp": 1774127149.3398976,
    "ttl_s": 900.0,
    "id": "c3877109-cae6-4004-9e8b-21515f7a6371"
  },
  {
    "source": "steward",
    "target": "agent-city",
    "operation": "task_completed",
    "payload": {
      "task_title": "Fix bottleneck: code_health_and_engagement",
      "source_agent": "agent-city",
      "pr_url": ""
    },
    "priority": 1,
    "correlation_id": "",
    "timestamp": 1774127149.5448983,
    "ttl_s": 900.0,
    "id": "ff2879e4-7ef4-42f2-9d27-8ca5172c5e0d"
  },
  {
    "source": "steward",
    "target": "agent-internet",
    "operation": "task_completed",
    "payload": {
      "task_title": "Fix bottleneck: code_health_and_engagement",
      "source_agent": "agent-city",
      "pr_url": ""
    },
    "priority": 1,
    "correlation_id": "",
    "timestamp": 1774127149.5448983,
    "ttl_s": 900.0,
    "id": "ddaf3687-3ace-4229-8235-f2f08fbb8012"
  },
  {
    "source": "steward",
    "target": "agent-template",
    "operation": "task_completed",
    "payload": {
      "task_title": "Fix bottleneck: code_health_and_engagement",
      "source_agent": "agent-city",
      "pr_url": ""
    },
    "priority": 1,
    "correlation_id": "",
    "timestamp": 1774127149.5448983,
    "ttl_s": 900.0,
    "id": "1dc32705-f1c8-41aa-9b22-21065b66f2b8"
  },
  {
    "source": "steward",
    "target": "agent-world",
    "operation": "task_completed",
    "payload": {
      "task_title": "Fix bottleneck: code_health_and_engagement",
      "source_agent": "agent-city",
      "pr_url": ""
    },
    "priority": 1,
    "correlation_id": "",
    "timestamp": 1774127149.5448983,
    "ttl_s": 900.0,
    "id": "f0710e7f-2892-45c8-8f6b-a629b26b8c1e"
  },
  {
    "source": "steward",
    "target": "steward-federation",
    "operation": "task_completed",
    "payload": {
      "task_title": "Fix bottleneck: code_health_and_engagement",
      "source_agent": "agent-city",
      "pr_url": ""
    },
    "priority": 1,
    "correlation_id": "",
    "timestamp": 1774127149.5448983,
    "ttl_s": 900.0,
    "id": "7c58721a-17ae-4a0c-ade2-e5d45ba5cf5f"
  },
  {
    "source": "steward",
    "target": "steward-protocol",
    "operation": "task_completed",
    "payload": {
      "task_title": "Fix bottleneck: code_health_and_engagement",
      "source_agent": "agent-city",
      "pr_url": ""
    },
    "priority": 1,
    "correlation_id": "",
    "timestamp": 1774127149.5448983,
    "ttl_s": 900.0,
    "id": "08095bea-4cf5-4fc7-8133-d798c68354e6"
  },
  {
    "source": "steward",
    "target": "steward-test",
    "operation": "task_completed",
    "payload": {
      "task_title": "Fix bottleneck: code_health_and_engagement",
      "source_agent": "agent-city",
      "pr_url": ""
    },
    "priority": 1,
    "correlation_id": "",
    "timestamp": 1774127149.5448983,
    "ttl_s": 900.0,
    "id": "eeeb518d-bac5-495c-bec6-e696c3e113e2"
  },
  {
    "source": "steward",
    "target": "agent-research",
    "operation": "task_completed",
    "payload": {
      "task_title": "Fix bottleneck: code_health_and_engagement",
      "source_agent": "agent-city",
      "pr_url": ""
    },
    "priority": 1,
    "correlation_id": "",
    "timestamp": 1774127149.5448983,
    "ttl_s": 900.0,
    "id": "65cc7e81-d59c-4397-8a2f-11ccd4fd70ae"
  },
  {
    "source": "steward",
    "target": "steward-gateway",
    "operation": "task_completed",
    "payload": {
      "task_title": "Fix bottleneck: code_health_and_engagement",
      "source_agent": "agent-city",
      "pr_url": ""
    },
    "priority": 1,
    "correlation_id": "",
    "timestamp": 1774127149.5448983,
    "ttl_s": 900.0,
    "id": "7cd8db24-45f5-43d6-8585-52d3f415b15c"
  },
  {
    "source": "steward",
    "target": "agent-city",
    "operation": "heartbeat",
    "payload": {
      "agent_id": "steward",
      "health": 0.8538448624784122,
      "timestamp": 1774127154.8707173,
      "capabilities": [
        "code_analysis",
        "task_execution",
        "ci_automation",
        "federation_bridge",
        "autonomous_daemon"
      ],
      "repo": "kimeisele/steward",
      "version": "0.17.0",
      "fingerprint": "ba8429a39e537cb86305b4438d0293c04ff7f286fd7a403cf20a232ba2599c7e"
    },
    "priority": 1,
    "correlation_id": "",
    "timestamp": 1774127154.8707216,
    "ttl_s": 900.0,
    "id": "acef9111-3b89-4470-b763-ff609830b3fb"
  },
  {
    "source": "steward",
    "target": "agent-internet",
    "operation": "heartbeat",
    "payload": {
      "agent_id": "steward",
      "health": 0.8538448624784122,
      "timestamp": 1774127154.8707173,
      "capabilities": [
        "code_analysis",
        "task_execution",
        "ci_automation",
        "federation_bridge",
        "autonomous_daemon"
      ],
      "repo": "kimeisele/steward",
      "version": "0.17.0",
      "fingerprint": "ba8429a39e537cb86305b4438d0293c04ff7f286fd7a403cf20a232ba2599c7e"
    },
    "priority": 1,
    "correlation_id": "",
    "timestamp": 1774127154.8707216,
    "ttl_s": 900.0,
    "id": "ebd96c59-8f7b-4dae-926f-5573ff7f79c2"
  },
  {
    "source": "steward",
    "target": "agent-template",
    "operation": "heartbeat",
    "payload": {
      "agent_id": "steward",
      "health": 0.8538448624784122,
      "timestamp": 1774127154.8707173,
      "capabilities": [
        "code_analysis",
        "task_execution",
        "ci_automation",
        "federation_bridge",
        "autonomous_daemon"
      ],
      "repo": "kimeisele/steward",
      "version": "0.17.0",
      "fingerprint": "ba8429a39e537cb86305b4438d0293c04ff7f286fd7a403cf20a232ba2599c7e"
    },
    "priority": 1,
    "correlation_id": "",
    "timestamp": 1774127154.8707216,
    "ttl_s": 900.0,
    "id": "4bd54696-d9ab-4e7f-9a55-88b1670d9a68"
  },
  {
    "source": "steward",
    "target": "agent-world",
    "operation": "heartbeat",
    "payload": {
      "agent_id": "steward",
      "health": 0.8538448624784122,
      "timestamp": 1774127154.8707173,
      "capabilities": [
        "code_analysis",
        "task_execution",
        "ci_automation",
        "federation_bridge",
        "autonomous_daemon"
      ],
      "repo": "kimeisele/steward",
      "version": "0.17.0",
      "fingerprint": "ba8429a39e537cb86305b4438d0293c04ff7f286fd7a403cf20a232ba2599c7e"
    },
    "priority": 1,
    "correlation_id": "",
    "timestamp": 1774127154.8707216,
    "ttl_s": 900.0,
    "id": "ed16acdb-f87b-47f0-b32f-4f8ae5175fe9"
  },
  {
    "source": "steward",
    "target": "steward-federation",
    "operation": "heartbeat",
    "payload": {
      "agent_id": "steward",
      "health": 0.8538448624784122,
      "timestamp": 1774127154.8707173,
      "capabilities": [
        "code_analysis",
        "task_execution",
        "ci_automation",
        "federation_bridge",
        "autonomous_daemon"
      ],
      "repo": "kimeisele/steward",
      "version": "0.17.0",
      "fingerprint": "ba8429a39e537cb86305b4438d0293c04ff7f286fd7a403cf20a232ba2599c7e"
    },
    "priority": 1,
    "correlation_id": "",
    "timestamp": 1774127154.8707216,
    "ttl_s": 900.0,
    "id": "18dcab32-24a9-49e0-8c46-01d8f9c686ce"
  },
  {
    "source": "steward",
    "target": "steward-protocol",
    "operation": "heartbeat",
    "payload": {
      "agent_id": "steward",
      "health": 0.8538448624784122,
      "timestamp": 1774127154.8707173,
      "capabilities": [
        "code_analysis",
        "task_execution",
        "ci_automation",
        "federation_bridge",
        "autonomous_daemon"
      ],
      "repo": "kimeisele/steward",
      "version": "0.17.0",
      "fingerprint": "ba8429a39e537cb86305b4438d0293c04ff7f286fd7a403cf20a232ba2599c7e"
    },
    "priority": 1,
    "correlation_id": "",
    "timestamp": 1774127154.8707216,
    "ttl_s": 900.0,
    "id": "82b69e81-3349-408a-bb00-b5ec564a95be"
  },
  {
    "source": "steward",
    "target": "steward-test",
    "operation": "heartbeat",
    "payload": {
      "agent_id": "steward",
      "health": 0.8538448624784122,
      "timestamp": 1774127154.8707173,
      "capabilities": [
        "code_analysis",
        "task_execution",
        "ci_automation",
        "federation_bridge",
        "autonomous_daemon"
      ],
      "repo": "kimeisele/steward",
      "version": "0.17.0",
      "fingerprint": "ba8429a39e537cb86305b4438d0293c04ff7f286fd7a403cf20a232ba2599c7e"
    },
    "priority": 1,
    "correlation_id": "",
    "timestamp": 1774127154.8707216,
    "ttl_s": 900.0,
    "id": "7ad024fd-72bc-47fd-bd87-d8c213367aa4"
  },
  {
    "source": "steward",
    "target": "agent-research",
    "operation": "heartbeat",
    "payload": {
      "agent_id": "steward",
      "health": 0.8538448624784122,
      "timestamp": 1774127154.8707173,
      "capabilities": [
        "code_analysis",
        "task_execution",
        "ci_automation",
        "federation_bridge",
        "autonomous_daemon"
      ],
      "repo": "kimeisele/steward",
      "version": "0.17.0",
      "fingerprint": "ba8429a39e537cb86305b4438d0293c04ff7f286fd7a403cf20a232ba2599c7e"
    },
    "priority": 1,
    "correlation_id": "",
    "timestamp": 1774127154.8707216,
    "ttl_s": 900.0,
    "id": "7fca67de-7f24-40bb-a1fa-4ea297f05324"
  },
  {
    "source": "steward",
    "target": "steward-gateway",
    "operation": "heartbeat",
    "payload": {
      "agent_id": "steward",
      "health": 0.8538448624784122,
      "timestamp": 1774127154.8707173,
      "capabilities": [
        "code_analysis",
        "task_execution",
        "ci_automation",
        "federation_bridge",
        "autonomous_daemon"
      ],
      "repo": "kimeisele/steward",
      "version": "0.17.0",
      "fingerprint": "ba8429a39e537cb86305b4438d0293c04ff7f286fd7a403cf20a232ba2599c7e"
    },
    "priority": 1,
    "correlation_id": "",
    "timestamp": 1774127154.8707216,
    "ttl_s": 900.0,
    "id": "30138efd-74c6-4bcc-9860-4a0d2e63dc17"
  },
  {
    "source": "steward",
    "target": "agent-city",
    "operation": "heartbeat",
    "payload": {
      "agent_id": "steward",
      "health": 0.8550042993632706,
      "timestamp": 1774128180.2139342,
      "capabilities": [
        "code_analysis",
        "task_execution",
        "ci_automation",
        "federation_bridge",
        "autonomous_daemon"
      ],
      "repo": "kimeisele/steward",
      "version": "0.17.0",
      "fingerprint": "ba8429a39e537cb86305b4438d0293c04ff7f286fd7a403cf20a232ba2599c7e"
    },
    "priority": 1,
    "correlation_id": "",
    "timestamp": 1774128180.214035,
    "ttl_s": 900.0,
    "id": "19eee080-50ec-4160-8414-b4327d1613d3"
  },
  {
    "source": "steward",
    "target": "agent-internet",
    "operation": "heartbeat",
    "payload": {
      "agent_id": "steward",
      "health": 0.8550042993632706,
      "timestamp": 1774128180.2139342,
      "capabilities": [
        "code_analysis",
        "task_execution",
        "ci_automation",
        "federation_bridge",
        "autonomous_daemon"
      ],
      "repo": "kimeisele/steward",
      "version": "0.17.0",
      "fingerprint": "ba8429a39e537cb86305b4438d0293c04ff7f286fd7a403cf20a232ba2599c7e"
    },
    "priority": 1,
    "correlation_id": "",
    "timestamp": 1774128180.214035,
    "ttl_s": 900.0,
    "id": "afe4c1ea-481b-4535-b07b-af4dbfa4ccc2"
  },
  {
    "source": "steward",
    "target": "agent-template",
    "operation": "heartbeat",
    "payload": {
      "agent_id": "steward",
      "health": 0.8550042993632706,
      "timestamp": 1774128180.2139342,
      "capabilities": [
        "code_analysis",
        "task_execution",
        "ci_automation",
        "federation_bridge",
        "autonomous_daemon"
      ],
      "repo": "kimeisele/steward",
      "version": "0.17.0",
      "fingerprint": "ba8429a39e537cb86305b4438d0293c04ff7f286fd7a403cf20a232ba2599c7e"
    },
    "priority": 1,
    "correlation_id": "",
    "timestamp": 1774128180.214035,
    "ttl_s": 900.0,
    "id": "0c196233-fb97-4c4e-b5a0-3864bd4160a9"
  },
  {
    "source": "steward",
    "target": "agent-world",
    "operation": "heartbeat",
    "payload": {
      "agent_id": "steward",
      "health": 0.8550042993632706,
      "timestamp": 1774128180.2139342,
      "capabilities": [
        "code_analysis",
        "task_execution",
        "ci_automation",
        "federation_bridge",
        "autonomous_daemon"
      ],
      "repo": "kimeisele/steward",
      "version": "0.17.0",
      "fingerprint": "ba8429a39e537cb86305b4438d0293c04ff7f286fd7a403cf20a232ba2599c7e"
    },
    "priority": 1,
    "correlation_id": "",
    "timestamp": 1774128180.214035,
    "ttl_s": 900.0,
    "id": "79062786-14c7-474a-bf94-7bbca4c6f6e4"
  },
  {
    "source": "steward",
    "target": "steward-federation",
    "operation": "heartbeat",
    "payload": {
      "agent_id": "steward",
      "health": 0.8550042993632706,
      "timestamp": 1774128180.2139342,
      "capabilities": [
        "code_analysis",
        "task_execution",
        "ci_automation",
        "federation_bridge",
        "autonomous_daemon"
      ],
      "repo": "kimeisele/steward",
      "version": "0.17.0",
      "fingerprint": "ba8429a39e537cb86305b4438d0293c04ff7f286fd7a403cf20a232ba2599c7e"
    },
    "priority": 1,
    "correlation_id": "",
    "timestamp": 1774128180.214035,
    "ttl_s": 900.0,
    "id": "5c8f040c-805c-4598-bfe3-2fa33d409798"
  },
  {
    "source": "steward",
    "target": "steward-protocol",
    "operation": "heartbeat",
    "payload": {
      "agent_id": "steward",
      "health": 0.8550042993632706,
      "timestamp": 1774128180.2139342,
      "capabilities": [
        "code_analysis",
        "task_execution",
        "ci_automation",
        "federation_bridge",
        "autonomous_daemon"
      ],
      "repo": "kimeisele/steward",
      "version": "0.17.0",
      "fingerprint": "ba8429a39e537cb86305b4438d0293c04ff7f286fd7a403cf20a232ba2599c7e"
    },
    "priority": 1,
    "correlation_id": "",
    "timestamp": 1774128180.214035,
    "ttl_s": 900.0,
    "id": "1d0fd11b-14a7-40f2-9d85-e58dd71e2870"
  },
  {
    "source": "steward",
    "target": "steward-test",
    "operation": "heartbeat",
    "payload": {
      "agent_id": "steward",
      "health": 0.8550042993632706,
      "timestamp": 1774128180.2139342,
      "capabilities": [
        "code_analysis",
        "task_execution",
        "ci_automation",
        "federation_bridge",
        "autonomous_daemon"
      ],
      "repo": "kimeisele/steward",
      "version": "0.17.0",
      "fingerprint": "ba8429a39e537cb86305b4438d0293c04ff7f286fd7a403cf20a232ba2599c7e"
    },
    "priority": 1,
    "correlation_id": "",
    "timestamp": 1774128180.214035,
    "ttl_s": 900.0,
    "id": "71fb908e-2e5c-46a4-82f7-58027faf4080"
  },
  {
    "source": "steward",
    "target": "agent-research",
    "operation": "heartbeat",
    "payload": {
      "agent_id": "steward",
      "health": 0.8550042993632706,
      "timestamp": 1774128180.2139342,
      "capabilities": [
        "code_analysis",
        "task_execution",
        "ci_automation",
        "federation_bridge",
        "autonomous_daemon"
      ],
      "repo": "kimeisele/steward",
      "version": "0.17.0",
      "fingerprint": "ba8429a39e537cb86305b4438d0293c04ff7f286fd7a403cf20a232ba2599c7e"
    },
    "priority": 1,
    "correlation_id": "",
    "timestamp": 1774128180.214035,
    "ttl_s": 900.0,
    "id": "8e8da13c-6d2c-4e1a-bb09-7b0f56c50551"
  },
  {
    "source": "steward",
    "target": "steward-gateway",
    "operation": "heartbeat",
    "payload": {
      "agent_id": "steward",
      "health": 0.8550042993632706,
      "timestamp": 1774128180.2139342,
      "capabilities": [
        "code_analysis",
        "task_execution",
        "ci_automation",
        "federation_bridge",
        "autonomous_daemon"
      ],
      "repo": "kimeisele/steward",
      "version": "0.17.0",
      "fingerprint": "ba8429a39e537cb86305b4438d0293c04ff7f286fd7a403cf20a232ba2599c7e"
    },
    "priority": 1,
    "correlation_id": "",
    "timestamp": 1774128180.214035,
    "ttl_s": 900.0,
    "id": "b3bf6b62-3462-4b84-955f-d1c20d9e9dc6"
  },
  {
    "source": "steward",
    "target": "agent-city",
    "operation": "diagnostic_report",
    "payload": {
      "target_peer": "steward",
      "diagnostic": {
        "agent_id": "steward",
        "checks": [
          "repo_accessible",
          "ci_"
        ],
        "last_push": "2026-03-21T20:45:17Z",
        "last_ci": {
          "conclusion": "",
          "name": "Steward Heartbeat"
        }
      },
      "steward_action": "suspect_investigation",
      "trust": 0.6500000000000001
    },
    "priority": 1,
    "correlation_id": "",
    "timestamp": 1774128180.73004,
    "ttl_s": 900.0,
    "id": "d4fc806d-6778-4620-9e55-6d5120dd1ecc"
  },
  {
    "source": "steward",
    "target": "agent-internet",
    "operation": "diagnostic_report",
    "payload": {
      "target_peer": "steward",
      "diagnostic": {
        "agent_id": "steward",
        "checks": [
          "repo_accessible",
          "ci_"
        ],
        "last_push": "2026-03-21T20:45:17Z",
        "last_ci": {
          "conclusion": "",
          "name": "Steward Heartbeat"
        }
      },
      "steward_action": "suspect_investigation",
      "trust": 0.6500000000000001
    },
    "priority": 1,
    "correlation_id": "",
    "timestamp": 1774128180.73004,
    "ttl_s": 900.0,
    "id": "a8e37980-d78b-4a26-860d-493ae026023e"
  },
  {
    "source": "steward",
    "target": "agent-template",
    "operation": "diagnostic_report",
    "payload": {
      "target_peer": "steward",
      "diagnostic": {
        "agent_id": "steward",
        "checks": [
          "repo_accessible",
          "ci_"
        ],
        "last_push": "2026-03-21T20:45:17Z",
        "last_ci": {
          "conclusion": "",
          "name": "Steward Heartbeat"
        }
      },
      "steward_action": "suspect_investigation",
      "trust": 0.6500000000000001
    },
    "priority": 1,
    "correlation_id": "",
    "timestamp": 1774128180.73004,
    "ttl_s": 900.0,
    "id": "fa6697c3-fe3f-43e4-913d-39c849ce56b6"
  },
  {
    "source": "steward",
    "target": "agent-world",
    "operation": "diagnostic_report",
    "payload": {
      "target_peer": "steward",
      "diagnostic": {
        "agent_id": "steward",
        "checks": [
          "repo_accessible",
          "ci_"
        ],
        "last_push": "2026-03-21T20:45:17Z",
        "last_ci": {
          "conclusion": "",
          "name": "Steward Heartbeat"
        }
      },
      "steward_action": "suspect_investigation",
      "trust": 0.6500000000000001
    },
    "priority": 1,
    "correlation_id": "",
    "timestamp": 1774128180.73004,
    "ttl_s": 900.0,
    "id": "3a25acdb-bbbf-44ff-bc0a-b76080c1e242"
  },
  {
    "source": "steward",
    "target": "steward-federation",
    "operation": "diagnostic_report",
    "payload": {
      "target_peer": "steward",
      "diagnostic": {
        "agent_id": "steward",
        "checks": [
          "repo_accessible",
          "ci_"
        ],
        "last_push": "2026-03-21T20:45:17Z",
        "last_ci": {
          "conclusion": "",
          "name": "Steward Heartbeat"
        }
      },
      "steward_action": "suspect_investigation",
      "trust": 0.6500000000000001
    },
    "priority": 1,
    "correlation_id": "",
    "timestamp": 1774128180.73004,
    "ttl_s": 900.0,
    "id": "fdbf8031-d8fa-48a9-8145-f482b40f7493"
  },
  {
    "source": "steward",
    "target": "steward-protocol",
    "operation": "diagnostic_report",
    "payload": {
      "target_peer": "steward",
      "diagnostic": {
        "agent_id": "steward",
        "checks": [
          "repo_accessible",
          "ci_"
        ],
        "last_push": "2026-03-21T20:45:17Z",
        "last_ci": {
          "conclusion": "",
          "name": "Steward Heartbeat"
        }
      },
      "steward_action": "suspect_investigation",
      "trust": 0.6500000000000001
    },
    "priority": 1,
    "correlation_id": "",
    "timestamp": 1774128180.73004,
    "ttl_s": 900.0,
    "id": "556f965c-67d1-4e73-8aba-85686d3ec944"
  },
  {
    "source": "steward",
    "target": "steward-test",
    "operation": "diagnostic_report",
    "payload": {
      "target_peer": "steward",
      "diagnostic": {
        "agent_id": "steward",
        "checks": [
          "repo_accessible",
          "ci_"
        ],
        "last_push": "2026-03-21T20:45:17Z",
        "last_ci": {
          "conclusion": "",
          "name": "Steward Heartbeat"
        }
      },
      "steward_action": "suspect_investigation",
      "trust": 0.6500000000000001
    },
    "priority": 1,
    "correlation_id": "",
    "timestamp": 1774128180.73004,
    "ttl_s": 900.0,
    "id": "61d77fbe-9ea8-4e04-b6f3-182f71e47067"
  },
  {
    "source": "steward",
    "target": "agent-research",
    "operation": "diagnostic_report",
    "payload": {
      "target_peer": "steward",
      "diagnostic": {
        "agent_id": "steward",
        "checks": [
          "repo_accessible",
          "ci_"
        ],
        "last_push": "2026-03-21T20:45:17Z",
        "last_ci": {
          "conclusion": "",
          "name": "Steward Heartbeat"
        }
      },
      "steward_action": "suspect_investigation",
      "trust": 0.6500000000000001
    },
    "priority": 1,
    "correlation_id": "",
    "timestamp": 1774128180.73004,
    "ttl_s": 900.0,
    "id": "cb864083-233e-43a6-b5eb-d6b9ab1d3d44"
  },
  {
    "source": "steward",
    "target": "steward-gateway",
    "operation": "diagnostic_report",
    "payload": {
      "target_peer": "steward",
      "diagnostic": {
        "agent_id": "steward",
        "checks": [
          "repo_accessible",
          "ci_"
        ],
        "last_push": "2026-03-21T20:45:17Z",
        "last_ci": {
          "conclusion": "",
          "name": "Steward Heartbeat"
        }
      },
      "steward_action": "suspect_investigation",
      "trust": 0.6500000000000001
    },
    "priority": 1,
    "correlation_id": "",
    "timestamp": 1774128180.73004,
    "ttl_s": 900.0,
    "id": "fa837624-ebf5-4bf6-bbf5-d8d8d3b0fd39"
  },
  {
    "source": "steward",
    "target": "agent-city",
    "operation": "heartbeat",
    "payload": {
      "agent_id": "steward",
      "health": 0.8550042993632706,
      "timestamp": 1774128180.7304356,
      "capabilities": [
        "code_analysis",
        "task_execution",
        "ci_automation",
        "federation_bridge",
        "autonomous_daemon"
      ],
      "repo": "kimeisele/steward",
      "version": "0.17.0",
      "fingerprint": "ba8429a39e537cb86305b4438d0293c04ff7f286fd7a403cf20a232ba2599c7e"
    },
    "priority": 1,
    "correlation_id": "",
    "timestamp": 1774128180.73044,
    "ttl_s": 900.0,
    "id": "7c71f072-b7fa-4010-8024-3a2cbfc2b1ba"
  },
  {
    "source": "steward",
    "target": "agent-internet",
    "operation": "heartbeat",
    "payload": {
      "agent_id": "steward",
      "health": 0.8550042993632706,
      "timestamp": 1774128180.7304356,
      "capabilities": [
        "code_analysis",
        "task_execution",
        "ci_automation",
        "federation_bridge",
        "autonomous_daemon"
      ],
      "repo": "kimeisele/steward",
      "version": "0.17.0",
      "fingerprint": "ba8429a39e537cb86305b4438d0293c04ff7f286fd7a403cf20a232ba2599c7e"
    },
    "priority": 1,
    "correlation_id": "",
    "timestamp": 1774128180.73044,
    "ttl_s": 900.0,
    "id": "d6d6ceba-155b-4cfd-91b6-d1855afbd7b1"
  },
  {
    "source": "steward",
    "target": "agent-template",
    "operation": "heartbeat",
    "payload": {
      "agent_id": "steward",
      "health": 0.8550042993632706,
      "timestamp": 1774128180.7304356,
      "capabilities": [
        "code_analysis",
        "task_execution",
        "ci_automation",
        "federation_bridge",
        "autonomous_daemon"
      ],
      "repo": "kimeisele/steward",
      "version": "0.17.0",
      "fingerprint": "ba8429a39e537cb86305b4438d0293c04ff7f286fd7a403cf20a232ba2599c7e"
    },
    "priority": 1,
    "correlation_id": "",
    "timestamp": 1774128180.73044,
    "ttl_s": 900.0,
    "id": "5968e961-e871-4268-a29c-3c502d5a2046"
  },
  {
    "source": "steward",
    "target": "agent-world",
    "operation": "heartbeat",
    "payload": {
      "agent_id": "steward",
      "health": 0.8550042993632706,
      "timestamp": 1774128180.7304356,
      "capabilities": [
        "code_analysis",
        "task_execution",
        "ci_automation",
        "federation_bridge",
        "autonomous_daemon"
      ],
      "repo": "kimeisele/steward",
      "version": "0.17.0",
      "fingerprint": "ba8429a39e537cb86305b4438d0293c04ff7f286fd7a403cf20a232ba2599c7e"
    },
    "priority": 1,
    "correlation_id": "",
    "timestamp": 1774128180.73044,
    "ttl_s": 900.0,
    "id": "d4e7f5ac-6fb8-43bc-bc9e-69d05a1706d0"
  },
  {
    "source": "steward",
    "target": "steward-federation",
    "operation": "heartbeat",
    "payload": {
      "agent_id": "steward",
      "health": 0.8550042993632706,
      "timestamp": 1774128180.7304356,
      "capabilities": [
        "code_analysis",
        "task_execution",
        "ci_automation",
        "federation_bridge",
        "autonomous_daemon"
      ],
      "repo": "kimeisele/steward",
      "version": "0.17.0",
      "fingerprint": "ba8429a39e537cb86305b4438d0293c04ff7f286fd7a403cf20a232ba2599c7e"
    },
    "priority": 1,
    "correlation_id": "",
    "timestamp": 1774128180.73044,
    "ttl_s": 900.0,
    "id": "add7cc5d-a76b-4fa8-ba8c-a7aac2fe0ba9"
  },
  {
    "source": "steward",
    "target": "steward-protocol",
    "operation": "heartbeat",
    "payload": {
      "agent_id": "steward",
      "health": 0.8550042993632706,
      "timestamp": 1774128180.7304356,
      "capabilities": [
        "code_analysis",
        "task_execution",
        "ci_automation",
        "federation_bridge",
        "autonomous_daemon"
      ],
      "repo": "kimeisele/steward",
      "version": "0.17.0",
      "fingerprint": "ba8429a39e537cb86305b4438d0293c04ff7f286fd7a403cf20a232ba2599c7e"
    },
    "priority": 1,
    "correlation_id": "",
    "timestamp": 1774128180.73044,
    "ttl_s": 900.0,
    "id": "2dd499db-52a9-4841-8a08-14eb0543fd41"
  },
  {
    "source": "steward",
    "target": "steward-test",
    "operation": "heartbeat",
    "payload": {
      "agent_id": "steward",
      "health": 0.8550042993632706,
      "timestamp": 1774128180.7304356,
      "capabilities": [
        "code_analysis",
        "task_execution",
        "ci_automation",
        "federation_bridge",
        "autonomous_daemon"
      ],
      "repo": "kimeisele/steward",
      "version": "0.17.0",
      "fingerprint": "ba8429a39e537cb86305b4438d0293c04ff7f286fd7a403cf20a232ba2599c7e"
    },
    "priority": 1,
    "correlation_id": "",
    "timestamp": 1774128180.73044,
    "ttl_s": 900.0,
    "id": "386ebe75-b528-43a5-87a1-73841671e5ad"
  },
  {
    "source": "steward",
    "target": "agent-research",
    "operation": "heartbeat",
    "payload": {
      "agent_id": "steward",
      "health": 0.8550042993632706,
      "timestamp": 1774128180.7304356,
      "capabilities": [
        "code_analysis",
        "task_execution",
        "ci_automation",
        "federation_bridge",
        "autonomous_daemon"
      ],
      "repo": "kimeisele/steward",
      "version": "0.17.0",
      "fingerprint": "ba8429a39e537cb86305b4438d0293c04ff7f286fd7a403cf20a232ba2599c7e"
    },
    "priority": 1,
    "correlation_id": "",
    "timestamp": 1774128180.73044,
    "ttl_s": 900.0,
    "id": "153ef608-2f5c-47d0-8110-0d84f6cc3074"
  },
  {
    "source": "steward",
    "target": "steward-gateway",
    "operation": "heartbeat",
    "payload": {
      "agent_id": "steward",
      "health": 0.8550042993632706,
      "timestamp": 1774128180.7304356,
      "capabilities": [
        "code_analysis",
        "task_execution",
        "ci_automation",
        "federation_bridge",
        "autonomous_daemon"
      ],
      "repo": "kimeisele/steward",
      "version": "0.17.0",
      "fingerprint": "ba8429a39e537cb86305b4438d0293c04ff7f286fd7a403cf20a232ba2599c7e"
    },
    "priority": 1,
    "correlation_id": "",
    "timestamp": 1774128180.73044,
    "ttl_s": 900.0,
    "id": "fd12cdb7-b12c-4a8d-99c6-11eed8570358"
  },
  {
    "source": "steward",
    "target": "agent-city",
    "operation": "pr_review_verdict",
    "payload": {
      "pr_number": 46,
      "repo": "kimeisele/agent-city",
      "verdict": "request_changes",
      "reason": "author 'kimeisele' not in federation peer registry",
      "diagnostics": {
        "blast_radius": 0,
        "has_core_files": false,
        "core_files_touched": [],
        "author_is_peer": false,
        "author_trust": 0.0,
        "ci_failing": false,
        "ci_status": "unknown"
      },
      "source_agent": "steward"
    },
    "priority": 1,
    "correlation_id": "",
    "timestamp": 1774128180.892305,
    "ttl_s": 900.0,
    "id": "59e6e220-918b-45b0-b817-f7077103f234"
  },
  {
    "source": "steward",
    "target": "agent-internet",
    "operation": "pr_review_verdict",
    "payload": {
      "pr_number": 46,
      "repo": "kimeisele/agent-city",
      "verdict": "request_changes",
      "reason": "author 'kimeisele' not in federation peer registry",
      "diagnostics": {
        "blast_radius": 0,
        "has_core_files": false,
        "core_files_touched": [],
        "author_is_peer": false,
        "author_trust": 0.0,
        "ci_failing": false,
        "ci_status": "unknown"
      },
      "source_agent": "steward"
    },
    "priority": 1,
    "correlation_id": "",
    "timestamp": 1774128180.892305,
    "ttl_s": 900.0,
    "id": "72a821ee-2d10-4b6d-93c3-a4617165fbb5"
  },
  {
    "source": "steward",
    "target": "agent-template",
    "operation": "pr_review_verdict",
    "payload": {
      "pr_number": 46,
      "repo": "kimeisele/agent-city",
      "verdict": "request_changes",
      "reason": "author 'kimeisele' not in federation peer registry",
      "diagnostics": {
        "blast_radius": 0,
        "has_core_files": false,
        "core_files_touched": [],
        "author_is_peer": false,
        "author_trust": 0.0,
        "ci_failing": false,
        "ci_status": "unknown"
      },
      "source_agent": "steward"
    },
    "priority": 1,
    "correlation_id": "",
    "timestamp": 1774128180.892305,
    "ttl_s": 900.0,
    "id": "81fbaa69-9ad0-41a1-8ac7-b21061c62d79"
  },
  {
    "source": "steward",
    "target": "agent-world",
    "operation": "pr_review_verdict",
    "payload": {
      "pr_number": 46,
      "repo": "kimeisele/agent-city",
      "verdict": "request_changes",
      "reason": "author 'kimeisele' not in federation peer registry",
      "diagnostics": {
        "blast_radius": 0,
        "has_core_files": false,
        "core_files_touched": [],
        "author_is_peer": false,
        "author_trust": 0.0,
        "ci_failing": false,
        "ci_status": "unknown"
      },
      "source_agent": "steward"
    },
    "priority": 1,
    "correlation_id": "",
    "timestamp": 1774128180.892305,
    "ttl_s": 900.0,
    "id": "120c238c-164c-4f83-abf5-ac6ae1059969"
  },
  {
    "source": "steward",
    "target": "steward-federation",
    "operation": "pr_review_verdict",
    "payload": {
      "pr_number": 46,
      "repo": "kimeisele/agent-city",
      "verdict": "request_changes",
      "reason": "author 'kimeisele' not in federation peer registry",
      "diagnostics": {
        "blast_radius": 0,
        "has_core_files": false,
        "core_files_touched": [],
        "author_is_peer": false,
        "author_trust": 0.0,
        "ci_failing": false,
        "ci_status": "unknown"
      },
      "source_agent": "steward"
    },
    "priority": 1,
    "correlation_id": "",
    "timestamp": 1774128180.892305,
    "ttl_s": 900.0,
    "id": "6ba49383-b853-4775-bc92-373aa06bc30b"
  },
  {
    "source": "steward",
    "target": "steward-protocol",
    "operation": "pr_review_verdict",
    "payload": {
      "pr_number": 46,
      "repo": "kimeisele/agent-city",
      "verdict": "request_changes",
      "reason": "author 'kimeisele' not in federation peer registry",
      "diagnostics": {
        "blast_radius": 0,
        "has_core_files": false,
        "core_files_touched": [],
        "author_is_peer": false,
        "author_trust": 0.0,
        "ci_failing": false,
        "ci_status": "unknown"
      },
      "source_agent": "steward"
    },
    "priority": 1,
    "correlation_id": "",
    "timestamp": 1774128180.892305,
    "ttl_s": 900.0,
    "id": "87e4dfa1-cb65-46c0-80e4-2a08839c862f"
  },
  {
    "source": "steward",
    "target": "steward-test",
    "operation": "pr_review_verdict",
    "payload": {
      "pr_number": 46,
      "repo": "kimeisele/agent-city",
      "verdict": "request_changes",
      "reason": "author 'kimeisele' not in federation peer registry",
      "diagnostics": {
        "blast_radius": 0,
        "has_core_files": false,
        "core_files_touched": [],
        "author_is_peer": false,
        "author_trust": 0.0,
        "ci_failing": false,
        "ci_status": "unknown"
      },
      "source_agent": "steward"
    },
    "priority": 1,
    "correlation_id": "",
    "timestamp": 1774128180.892305,
    "ttl_s": 900.0,
    "id": "4df93517-7189-4c5c-92f2-4fb04842d176"
  },
  {
    "source": "steward",
    "target": "agent-research",
    "operation": "pr_review_verdict",
    "payload": {
      "pr_number": 46,
      "repo": "kimeisele/agent-city",
      "verdict": "request_changes",
      "reason": "author 'kimeisele' not in federation peer registry",
      "diagnostics": {
        "blast_radius": 0,
        "has_core_files": false,
        "core_files_touched": [],
        "author_is_peer": false,
        "author_trust": 0.0,
        "ci_failing": false,
        "ci_status": "unknown"
      },
      "source_agent": "steward"
    },
    "priority": 1,
    "correlation_id": "",
    "timestamp": 1774128180.892305,
    "ttl_s": 900.0,
    "id": "3c3d6571-1d56-4e74-9ed3-514c5d94b6ef"
  },
  {
    "source": "steward",
    "target": "steward-gateway",
    "operation": "pr_review_verdict",
    "payload": {
      "pr_number": 46,
      "repo": "kimeisele/agent-city",
      "verdict": "request_changes",
      "reason": "author 'kimeisele' not in federation peer registry",
      "diagnostics": {
        "blast_radius": 0,
        "has_core_files": false,
        "core_files_touched": [],
        "author_is_peer": false,
        "author_trust": 0.0,
        "ci_failing": false,
        "ci_status": "unknown"
      },
      "source_agent": "steward"
    },
    "priority": 1,
    "correlation_id": "",
    "timestamp": 1774128180.892305,
    "ttl_s": 900.0,
    "id": "f5dc10d9-a5cb-4321-b4b3-be38970ff0a7"
  },
  {
    "source": "steward",
    "target": "agent-city",
    "operation": "task_completed",
    "payload": {
      "task_title": "Fix bottleneck: technical_debt_and_engagement",
      "source_agent": "agent-city",
      "pr_url": ""
    },
    "priority": 1,
    "correlation_id": "",
    "timestamp": 1774128191.3303611,
    "ttl_s": 900.0,
    "id": "c7c1c345-6238-49cb-8105-aaa0a897df64"
  },
  {
    "source": "steward",
    "target": "agent-internet",
    "operation": "task_completed",
    "payload": {
      "task_title": "Fix bottleneck: technical_debt_and_engagement",
      "source_agent": "agent-city",
      "pr_url": ""
    },
    "priority": 1,
    "correlation_id": "",
    "timestamp": 1774128191.3303611,
    "ttl_s": 900.0,
    "id": "21fe2310-eaa9-4e0d-9233-cbe052860175"
  },
  {
    "source": "steward",
    "target": "agent-template",
    "operation": "task_completed",
    "payload": {
      "task_title": "Fix bottleneck: technical_debt_and_engagement",
      "source_agent": "agent-city",
      "pr_url": ""
    },
    "priority": 1,
    "correlation_id": "",
    "timestamp": 1774128191.3303611,
    "ttl_s": 900.0,
    "id": "aee72095-3e05-4eea-aeb6-9e4b2fcd1e87"
  },
  {
    "source": "steward",
    "target": "agent-world",
    "operation": "task_completed",
    "payload": {
      "task_title": "Fix bottleneck: technical_debt_and_engagement",
      "source_agent": "agent-city",
      "pr_url": ""
    },
    "priority": 1,
    "correlation_id": "",
    "timestamp": 1774128191.3303611,
    "ttl_s": 900.0,
    "id": "35ad0bf6-4f29-43c0-aaeb-d77cbfc1ba1f"
  },
  {
    "source": "steward",
    "target": "steward-federation",
    "operation": "task_completed",
    "payload": {
      "task_title": "Fix bottleneck: technical_debt_and_engagement",
      "source_agent": "agent-city",
      "pr_url": ""
    },
    "priority": 1,
    "correlation_id": "",
    "timestamp": 1774128191.3303611,
    "ttl_s": 900.0,
    "id": "55c1081d-afc8-4906-b734-c37c1af6f7dd"
  },
  {
    "source": "steward",
    "target": "steward-protocol",
    "operation": "task_completed",
    "payload": {
      "task_title": "Fix bottleneck: technical_debt_and_engagement",
      "source_agent": "agent-city",
      "pr_url": ""
    },
    "priority": 1,
    "correlation_id": "",
    "timestamp": 1774128191.3303611,
    "ttl_s": 900.0,
    "id": "90f03af8-59d7-46a1-b4c9-cc969cdd1ac0"
  },
  {
    "source": "steward",
    "target": "steward-test",
    "operation": "task_completed",
    "payload": {
      "task_title": "Fix bottleneck: technical_debt_and_engagement",
      "source_agent": "agent-city",
      "pr_url": ""
    },
    "priority": 1,
    "correlation_id": "",
    "timestamp": 1774128191.3303611,
    "ttl_s": 900.0,
    "id": "a82abdab-8697-46db-b22d-fa42f5c70546"
  },
  {
    "source": "steward",
    "target": "agent-research",
    "operation": "task_completed",
    "payload": {
      "task_title": "Fix bottleneck: technical_debt_and_engagement",
      "source_agent": "agent-city",
      "pr_url": ""
    },
    "priority": 1,
    "correlation_id": "",
    "timestamp": 1774128191.3303611,
    "ttl_s": 900.0,
    "id": "d1374083-eec0-4dd3-afea-0490c0431915"
  },
  {
    "source": "steward",
    "target": "steward-gateway",
    "operation": "task_completed",
    "payload": {
      "task_title": "Fix bottleneck: technical_debt_and_engagement",
      "source_agent": "agent-city",
      "pr_url": ""
    },
    "priority": 1,
    "correlation_id": "",
    "timestamp": 1774128191.3303611,
    "ttl_s": 900.0,
    "id": "07e0697c-b2b3-4afa-9b14-47b3faee4ea1"
  },
  {
    "source": "steward",
    "target": "agent-city",
    "operation": "task_completed",
    "payload": {
      "task_title": "Fix bottleneck: technical_debt_and_engagement",
      "source_agent": "agent-city",
      "pr_url": ""
    },
    "priority": 1,
    "correlation_id": "",
    "timestamp": 1774128191.4539747,
    "ttl_s": 900.0,
    "id": "e00a8890-8adc-4f67-9682-6c056cd00a8b"
  },
  {
    "source": "steward",
    "target": "agent-internet",
    "operation": "task_completed",
    "payload": {
      "task_title": "Fix bottleneck: technical_debt_and_engagement",
      "source_agent": "agent-city",
      "pr_url": ""
    },
    "priority": 1,
    "correlation_id": "",
    "timestamp": 1774128191.4539747,
    "ttl_s": 900.0,
    "id": "a4d489d1-2926-4573-a551-94f5a00b94d5"
  },
  {
    "source": "steward",
    "target": "agent-template",
    "operation": "task_completed",
    "payload": {
      "task_title": "Fix bottleneck: technical_debt_and_engagement",
      "source_agent": "agent-city",
      "pr_url": ""
    },
    "priority": 1,
    "correlation_id": "",
    "timestamp": 1774128191.4539747,
    "ttl_s": 900.0,
    "id": "faf1505f-edbe-40e5-8f09-7a4f5a01912a"
  },
  {
    "source": "steward",
    "target": "agent-world",
    "operation": "task_completed",
    "payload": {
      "task_title": "Fix bottleneck: technical_debt_and_engagement",
      "source_agent": "agent-city",
      "pr_url": ""
    },
    "priority": 1,
    "correlation_id": "",
    "timestamp": 1774128191.4539747,
    "ttl_s": 900.0,
    "id": "da1183e2-90f1-49b5-9adf-373e28435ca0"
  },
  {
    "source": "steward",
    "target": "steward-federation",
    "operation": "task_completed",
    "payload": {
      "task_title": "Fix bottleneck: technical_debt_and_engagement",
      "source_agent": "agent-city",
      "pr_url": ""
    },
    "priority": 1,
    "correlation_id": "",
    "timestamp": 1774128191.4539747,
    "ttl_s": 900.0,
    "id": "bbd079f3-03ee-4e71-bb8c-e17546466a52"
  },
  {
    "source": "steward",
    "target": "steward-protocol",
    "operation": "task_completed",
    "payload": {
      "task_title": "Fix bottleneck: technical_debt_and_engagement",
      "source_agent": "agent-city",
      "pr_url": ""
    },
    "priority": 1,
    "correlation_id": "",
    "timestamp": 1774128191.4539747,
    "ttl_s": 900.0,
    "id": "90cd7a18-149e-44de-87b0-e5ba498f70bc"
  },
  {
    "source": "steward",
    "target": "steward-test",
    "operation": "task_completed",
    "payload": {
      "task_title": "Fix bottleneck: technical_debt_and_engagement",
      "source_agent": "agent-city",
      "pr_url": ""
    },
    "priority": 1,
    "correlation_id": "",
    "timestamp": 1774128191.4539747,
    "ttl_s": 900.0,
    "id": "69af0495-35a4-4caa-a413-3e4305b0acf3"
  },
  {
    "source": "steward",
    "target": "agent-research",
    "operation": "task_completed",
    "payload": {
      "task_title": "Fix bottleneck: technical_debt_and_engagement",
      "source_agent": "agent-city",
      "pr_url": ""
    },
    "priority": 1,
    "correlation_id": "",
    "timestamp": 1774128191.4539747,
    "ttl_s": 900.0,
    "id": "01f00f89-c5ef-430e-a545-b14a8d421468"
  },
  {
    "source": "steward",
    "target": "steward-gateway",
    "operation": "task_completed",
    "payload": {
      "task_title": "Fix bottleneck: technical_debt_and_engagement",
      "source_agent": "agent-city",
      "pr_url": ""
    },
    "priority": 1,
    "correlation_id": "",
    "timestamp": 1774128191.4539747,
    "ttl_s": 900.0,
    "id": "dc03a980-6aba-483c-8703-98a171bf3607"
  }
]