[
  {
    "source": "steward",
    "target": "agent-city",
    "operation": "heartbeat",
    "payload": {
      "agent_id": "steward",
      "health": 0.8575551117523086,
      "timestamp": 1774020560.4971397,
      "capabilities": [
        "code_analysis",
        "task_execution",
        "ci_automation",
        "federation_bridge",
        "autonomous_daemon"
      ],
      "repo": "kimeisele/steward",
      "version": "0.17.0",
      "fingerprint": "ba8429a39e537cb86305b4438d0293c04ff7f286fd7a403cf20a232ba2599c7e"
    },
    "timestamp": 1774020560.497144,
    "priority": 1,
    "correlation_id": "",
    "ttl_s": 900.0,
    "id": "acc2bdb7-cb38-4650-8e59-d235b7e70faa"
  },
  {
    "source": "steward",
    "target": "agent-internet",
    "operation": "heartbeat",
    "payload": {
      "agent_id": "steward",
      "health": 0.8575551117523086,
      "timestamp": 1774020560.4971397,
      "capabilities": [
        "code_analysis",
        "task_execution",
        "ci_automation",
        "federation_bridge",
        "autonomous_daemon"
      ],
      "repo": "kimeisele/steward",
      "version": "0.17.0",
      "fingerprint": "ba8429a39e537cb86305b4438d0293c04ff7f286fd7a403cf20a232ba2599c7e"
    },
    "timestamp": 1774020560.497144,
    "priority": 1,
    "correlation_id": "",
    "ttl_s": 900.0,
    "id": "d35276f1-695b-4928-a34d-d151eaf77577"
  },
  {
    "source": "steward",
    "target": "agent-template",
    "operation": "heartbeat",
    "payload": {
      "agent_id": "steward",
      "health": 0.8575551117523086,
      "timestamp": 1774020560.4971397,
      "capabilities": [
        "code_analysis",
        "task_execution",
        "ci_automation",
        "federation_bridge",
        "autonomous_daemon"
      ],
      "repo": "kimeisele/steward",
      "version": "0.17.0",
      "fingerprint": "ba8429a39e537cb86305b4438d0293c04ff7f286fd7a403cf20a232ba2599c7e"
    },
    "timestamp": 1774020560.497144,
    "priority": 1,
    "correlation_id": "",
    "ttl_s": 900.0,
    "id": "e7997f3e-648a-4f4c-be11-d82acad4584b"
  },
  {
    "source": "steward",
    "target": "agent-world",
    "operation": "heartbeat",
    "payload": {
      "agent_id": "steward",
      "health": 0.8575551117523086,
      "timestamp": 1774020560.4971397,
      "capabilities": [
        "code_analysis",
        "task_execution",
        "ci_automation",
        "federation_bridge",
        "autonomous_daemon"
      ],
      "repo": "kimeisele/steward",
      "version": "0.17.0",
      "fingerprint": "ba8429a39e537cb86305b4438d0293c04ff7f286fd7a403cf20a232ba2599c7e"
    },
    "timestamp": 1774020560.497144,
    "priority": 1,
    "correlation_id": "",
    "ttl_s": 900.0,
    "id": "b0f18ae8-434b-4b8d-ae83-1b39c2dc0ab3"
  },
  {
    "source": "steward",
    "target": "steward-federation",
    "operation": "heartbeat",
    "payload": {
      "agent_id": "steward",
      "health": 0.8575551117523086,
      "timestamp": 1774020560.4971397,
      "capabilities": [
        "code_analysis",
        "task_execution",
        "ci_automation",
        "federation_bridge",
        "autonomous_daemon"
      ],
      "repo": "kimeisele/steward",
      "version": "0.17.0",
      "fingerprint": "ba8429a39e537cb86305b4438d0293c04ff7f286fd7a403cf20a232ba2599c7e"
    },
    "timestamp": 1774020560.497144,
    "priority": 1,
    "correlation_id": "",
    "ttl_s": 900.0,
    "id": "0dbd8871-b3cf-4711-83f8-c0127dd61a8a"
  },
  {
    "source": "steward",
    "target": "steward-protocol",
    "operation": "heartbeat",
    "payload": {
      "agent_id": "steward",
      "health": 0.8575551117523086,
      "timestamp": 1774020560.4971397,
      "capabilities": [
        "code_analysis",
        "task_execution",
        "ci_automation",
        "federation_bridge",
        "autonomous_daemon"
      ],
      "repo": "kimeisele/steward",
      "version": "0.17.0",
      "fingerprint": "ba8429a39e537cb86305b4438d0293c04ff7f286fd7a403cf20a232ba2599c7e"
    },
    "timestamp": 1774020560.497144,
    "priority": 1,
    "correlation_id": "",
    "ttl_s": 900.0,
    "id": "410d8b91-dfde-4c0f-8b2a-65a07265ca63"
  },
  {
    "source": "steward",
    "target": "steward-test",
    "operation": "heartbeat",
    "payload": {
      "agent_id": "steward",
      "health": 0.8575551117523086,
      "timestamp": 1774020560.4971397,
      "capabilities": [
        "code_analysis",
        "task_execution",
        "ci_automation",
        "federation_bridge",
        "autonomous_daemon"
      ],
      "repo": "kimeisele/steward",
      "version": "0.17.0",
      "fingerprint": "ba8429a39e537cb86305b4438d0293c04ff7f286fd7a403cf20a232ba2599c7e"
    },
    "timestamp": 1774020560.497144,
    "priority": 1,
    "correlation_id": "",
    "ttl_s": 900.0,
    "id": "5e88f7f1-f17a-4a53-baed-c58229c2cede"
  },
  {
    "source": "steward",
    "target": "agent-research",
    "operation": "heartbeat",
    "payload": {
      "agent_id": "steward",
      "health": 0.8575551117523086,
      "timestamp": 1774020560.4971397,
      "capabilities": [
        "code_analysis",
        "task_execution",
        "ci_automation",
        "federation_bridge",
        "autonomous_daemon"
      ],
      "repo": "kimeisele/steward",
      "version": "0.17.0",
      "fingerprint": "ba8429a39e537cb86305b4438d0293c04ff7f286fd7a403cf20a232ba2599c7e"
    },
    "timestamp": 1774020560.497144,
    "priority": 1,
    "correlation_id": "",
    "ttl_s": 900.0,
    "id": "57a26d53-55a5-40cb-bff1-e8f22f19a4d3"
  },
  {
    "source": "steward",
    "target": "steward-gateway",
    "operation": "heartbeat",
    "payload": {
      "agent_id": "steward",
      "health": 0.8575551117523086,
      "timestamp": 1774020560.4971397,
      "capabilities": [
        "code_analysis",
        "task_execution",
        "ci_automation",
        "federation_bridge",
        "autonomous_daemon"
      ],
      "repo": "kimeisele/steward",
      "version": "0.17.0",
      "fingerprint": "ba8429a39e537cb86305b4438d0293c04ff7f286fd7a403cf20a232ba2599c7e"
    },
    "timestamp": 1774020560.497144,
    "priority": 1,
    "correlation_id": "",
    "ttl_s": 900.0,
    "id": "96c67804-e3fb-41cd-8da9-63672d997779"
  },
  {
    "source": "steward",
    "target": "agent-city",
    "operation": "heartbeat",
    "payload": {
      "agent_id": "steward",
      "health": 0.8554772010707079,
      "timestamp": 1774019174.0830777,
      "capabilities": [
        "code_analysis",
        "task_execution",
        "ci_automation",
        "federation_bridge",
        "autonomous_daemon"
      ],
      "repo": "kimeisele/steward",
      "version": "0.17.0",
      "fingerprint": "ba8429a39e537cb86305b4438d0293c04ff7f286fd7a403cf20a232ba2599c7e"
    },
    "timestamp": 1774019174.0830839,
    "priority": 1,
    "correlation_id": "",
    "ttl_s": 900.0,
    "id": "a406a842-637b-41eb-a3af-5cf2a5c5f2ed"
  },
  {
    "source": "steward",
    "target": "agent-internet",
    "operation": "heartbeat",
    "payload": {
      "agent_id": "steward",
      "health": 0.8554772010707079,
      "timestamp": 1774019174.0830777,
      "capabilities": [
        "code_analysis",
        "task_execution",
        "ci_automation",
        "federation_bridge",
        "autonomous_daemon"
      ],
      "repo": "kimeisele/steward",
      "version": "0.17.0",
      "fingerprint": "ba8429a39e537cb86305b4438d0293c04ff7f286fd7a403cf20a232ba2599c7e"
    },
    "timestamp": 1774019174.0830839,
    "priority": 1,
    "correlation_id": "",
    "ttl_s": 900.0,
    "id": "f103ac6d-0cf4-41e4-bd97-57b8de1e120d"
  },
  {
    "source": "steward",
    "target": "agent-template",
    "operation": "heartbeat",
    "payload": {
      "agent_id": "steward",
      "health": 0.8554772010707079,
      "timestamp": 1774019174.0830777,
      "capabilities": [
        "code_analysis",
        "task_execution",
        "ci_automation",
        "federation_bridge",
        "autonomous_daemon"
      ],
      "repo": "kimeisele/steward",
      "version": "0.17.0",
      "fingerprint": "ba8429a39e537cb86305b4438d0293c04ff7f286fd7a403cf20a232ba2599c7e"
    },
    "timestamp": 1774019174.0830839,
    "priority": 1,
    "correlation_id": "",
    "ttl_s": 900.0,
    "id": "cc8f0be4-5a4a-4102-8bdf-599c595838a5"
  },
  {
    "source": "steward",
    "target": "agent-world",
    "operation": "heartbeat",
    "payload": {
      "agent_id": "steward",
      "health": 0.8554772010707079,
      "timestamp": 1774019174.0830777,
      "capabilities": [
        "code_analysis",
        "task_execution",
        "ci_automation",
        "federation_bridge",
        "autonomous_daemon"
      ],
      "repo": "kimeisele/steward",
      "version": "0.17.0",
      "fingerprint": "ba8429a39e537cb86305b4438d0293c04ff7f286fd7a403cf20a232ba2599c7e"
    },
    "timestamp": 1774019174.0830839,
    "priority": 1,
    "correlation_id": "",
    "ttl_s": 900.0,
    "id": "e87f7860-9d5e-493f-8072-58c4d073be71"
  },
  {
    "source": "steward",
    "target": "steward-federation",
    "operation": "heartbeat",
    "payload": {
      "agent_id": "steward",
      "health": 0.8554772010707079,
      "timestamp": 1774019174.0830777,
      "capabilities": [
        "code_analysis",
        "task_execution",
        "ci_automation",
        "federation_bridge",
        "autonomous_daemon"
      ],
      "repo": "kimeisele/steward",
      "version": "0.17.0",
      "fingerprint": "ba8429a39e537cb86305b4438d0293c04ff7f286fd7a403cf20a232ba2599c7e"
    },
    "timestamp": 1774019174.0830839,
    "priority": 1,
    "correlation_id": "",
    "ttl_s": 900.0,
    "id": "60821307-f6bf-412f-9df2-e6d4d33d9d54"
  },
  {
    "source": "steward",
    "target": "steward-protocol",
    "operation": "heartbeat",
    "payload": {
      "agent_id": "steward",
      "health": 0.8554772010707079,
      "timestamp": 1774019174.0830777,
      "capabilities": [
        "code_analysis",
        "task_execution",
        "ci_automation",
        "federation_bridge",
        "autonomous_daemon"
      ],
      "repo": "kimeisele/steward",
      "version": "0.17.0",
      "fingerprint": "ba8429a39e537cb86305b4438d0293c04ff7f286fd7a403cf20a232ba2599c7e"
    },
    "timestamp": 1774019174.0830839,
    "priority": 1,
    "correlation_id": "",
    "ttl_s": 900.0,
    "id": "74785f0e-9a25-4359-aadc-1c8f49b16b74"
  },
  {
    "source": "steward",
    "target": "steward-test",
    "operation": "heartbeat",
    "payload": {
      "agent_id": "steward",
      "health": 0.8554772010707079,
      "timestamp": 1774019174.0830777,
      "capabilities": [
        "code_analysis",
        "task_execution",
        "ci_automation",
        "federation_bridge",
        "autonomous_daemon"
      ],
      "repo": "kimeisele/steward",
      "version": "0.17.0",
      "fingerprint": "ba8429a39e537cb86305b4438d0293c04ff7f286fd7a403cf20a232ba2599c7e"
    },
    "timestamp": 1774019174.0830839,
    "priority": 1,
    "correlation_id": "",
    "ttl_s": 900.0,
    "id": "3240bd6b-5783-4ac6-b673-dcc0fbf95ac0"
  },
  {
    "source": "steward",
    "target": "agent-research",
    "operation": "heartbeat",
    "payload": {
      "agent_id": "steward",
      "health": 0.8554772010707079,
      "timestamp": 1774019174.0830777,
      "capabilities": [
        "code_analysis",
        "task_execution",
        "ci_automation",
        "federation_bridge",
        "autonomous_daemon"
      ],
      "repo": "kimeisele/steward",
      "version": "0.17.0",
      "fingerprint": "ba8429a39e537cb86305b4438d0293c04ff7f286fd7a403cf20a232ba2599c7e"
    },
    "timestamp": 1774019174.0830839,
    "priority": 1,
    "correlation_id": "",
    "ttl_s": 900.0,
    "id": "d83eb19f-1303-4c56-862d-f3b3ffd5616b"
  },
  {
    "source": "steward",
    "target": "steward-gateway",
    "operation": "heartbeat",
    "payload": {
      "agent_id": "steward",
      "health": 0.8554772010707079,
      "timestamp": 1774019174.0830777,
      "capabilities": [
        "code_analysis",
        "task_execution",
        "ci_automation",
        "federation_bridge",
        "autonomous_daemon"
      ],
      "repo": "kimeisele/steward",
      "version": "0.17.0",
      "fingerprint": "ba8429a39e537cb86305b4438d0293c04ff7f286fd7a403cf20a232ba2599c7e"
    },
    "timestamp": 1774019174.0830839,
    "priority": 1,
    "correlation_id": "",
    "ttl_s": 900.0,
    "id": "46b68305-df1f-4d62-acc7-17caf0a0e940"
  },
  {
    "source": "steward",
    "target": "agent-city",
    "operation": "heartbeat",
    "payload": {
      "agent_id": "steward",
      "health": 0.8575551117523086,
      "timestamp": 1774020560.3068097,
      "capabilities": [
        "code_analysis",
        "task_execution",
        "ci_automation",
        "federation_bridge",
        "autonomous_daemon"
      ],
      "repo": "kimeisele/steward",
      "version": "0.17.0",
      "fingerprint": "ba8429a39e537cb86305b4438d0293c04ff7f286fd7a403cf20a232ba2599c7e"
    },
    "timestamp": 1774020560.3069494,
    "priority": 1,
    "correlation_id": "",
    "ttl_s": 900.0,
    "id": "718dc530-3622-4ecd-bf5f-741da9776ac8"
  },
  {
    "source": "steward",
    "target": "agent-internet",
    "operation": "heartbeat",
    "payload": {
      "agent_id": "steward",
      "health": 0.8575551117523086,
      "timestamp": 1774020560.3068097,
      "capabilities": [
        "code_analysis",
        "task_execution",
        "ci_automation",
        "federation_bridge",
        "autonomous_daemon"
      ],
      "repo": "kimeisele/steward",
      "version": "0.17.0",
      "fingerprint": "ba8429a39e537cb86305b4438d0293c04ff7f286fd7a403cf20a232ba2599c7e"
    },
    "timestamp": 1774020560.3069494,
    "priority": 1,
    "correlation_id": "",
    "ttl_s": 900.0,
    "id": "f8f8df3c-a714-4ff9-ab07-9ac85baf54d6"
  },
  {
    "source": "steward",
    "target": "agent-template",
    "operation": "heartbeat",
    "payload": {
      "agent_id": "steward",
      "health": 0.8575551117523086,
      "timestamp": 1774020560.3068097,
      "capabilities": [
        "code_analysis",
        "task_execution",
        "ci_automation",
        "federation_bridge",
        "autonomous_daemon"
      ],
      "repo": "kimeisele/steward",
      "version": "0.17.0",
      "fingerprint": "ba8429a39e537cb86305b4438d0293c04ff7f286fd7a403cf20a232ba2599c7e"
    },
    "timestamp": 1774020560.3069494,
    "priority": 1,
    "correlation_id": "",
    "ttl_s": 900.0,
    "id": "bc140660-3e4d-4ed4-906d-8c976c30e9b1"
  },
  {
    "source": "steward",
    "target": "agent-world",
    "operation": "heartbeat",
    "payload": {
      "agent_id": "steward",
      "health": 0.8575551117523086,
      "timestamp": 1774020560.3068097,
      "capabilities": [
        "code_analysis",
        "task_execution",
        "ci_automation",
        "federation_bridge",
        "autonomous_daemon"
      ],
      "repo": "kimeisele/steward",
      "version": "0.17.0",
      "fingerprint": "ba8429a39e537cb86305b4438d0293c04ff7f286fd7a403cf20a232ba2599c7e"
    },
    "timestamp": 1774020560.3069494,
    "priority": 1,
    "correlation_id": "",
    "ttl_s": 900.0,
    "id": "20044025-efb7-441b-81b0-513ac812916e"
  },
  {
    "source": "steward",
    "target": "steward-federation",
    "operation": "heartbeat",
    "payload": {
      "agent_id": "steward",
      "health": 0.8575551117523086,
      "timestamp": 1774020560.3068097,
      "capabilities": [
        "code_analysis",
        "task_execution",
        "ci_automation",
        "federation_bridge",
        "autonomous_daemon"
      ],
      "repo": "kimeisele/steward",
      "version": "0.17.0",
      "fingerprint": "ba8429a39e537cb86305b4438d0293c04ff7f286fd7a403cf20a232ba2599c7e"
    },
    "timestamp": 1774020560.3069494,
    "priority": 1,
    "correlation_id": "",
    "ttl_s": 900.0,
    "id": "43918d98-b2d7-43cf-bcfe-6f7dbeb16871"
  },
  {
    "source": "steward",
    "target": "steward-protocol",
    "operation": "heartbeat",
    "payload": {
      "agent_id": "steward",
      "health": 0.8575551117523086,
      "timestamp": 1774020560.3068097,
      "capabilities": [
        "code_analysis",
        "task_execution",
        "ci_automation",
        "federation_bridge",
        "autonomous_daemon"
      ],
      "repo": "kimeisele/steward",
      "version": "0.17.0",
      "fingerprint": "ba8429a39e537cb86305b4438d0293c04ff7f286fd7a403cf20a232ba2599c7e"
    },
    "timestamp": 1774020560.3069494,
    "priority": 1,
    "correlation_id": "",
    "ttl_s": 900.0,
    "id": "fa4add56-e87d-4774-8811-38059b56a000"
  },
  {
    "source": "steward",
    "target": "steward-test",
    "operation": "heartbeat",
    "payload": {
      "agent_id": "steward",
      "health": 0.8575551117523086,
      "timestamp": 1774020560.3068097,
      "capabilities": [
        "code_analysis",
        "task_execution",
        "ci_automation",
        "federation_bridge",
        "autonomous_daemon"
      ],
      "repo": "kimeisele/steward",
      "version": "0.17.0",
      "fingerprint": "ba8429a39e537cb86305b4438d0293c04ff7f286fd7a403cf20a232ba2599c7e"
    },
    "timestamp": 1774020560.3069494,
    "priority": 1,
    "correlation_id": "",
    "ttl_s": 900.0,
    "id": "11d2e3a8-d3e6-45ca-b60b-479568411091"
  },
  {
    "source": "steward",
    "target": "agent-research",
    "operation": "heartbeat",
    "payload": {
      "agent_id": "steward",
      "health": 0.8575551117523086,
      "timestamp": 1774020560.3068097,
      "capabilities": [
        "code_analysis",
        "task_execution",
        "ci_automation",
        "federation_bridge",
        "autonomous_daemon"
      ],
      "repo": "kimeisele/steward",
      "version": "0.17.0",
      "fingerprint": "ba8429a39e537cb86305b4438d0293c04ff7f286fd7a403cf20a232ba2599c7e"
    },
    "timestamp": 1774020560.3069494,
    "priority": 1,
    "correlation_id": "",
    "ttl_s": 900.0,
    "id": "7d8d0cab-c69b-4874-ad59-5680ff152d77"
  },
  {
    "source": "steward",
    "target": "steward-gateway",
    "operation": "heartbeat",
    "payload": {
      "agent_id": "steward",
      "health": 0.8575551117523086,
      "timestamp": 1774020560.3068097,
      "capabilities": [
        "code_analysis",
        "task_execution",
        "ci_automation",
        "federation_bridge",
        "autonomous_daemon"
      ],
      "repo": "kimeisele/steward",
      "version": "0.17.0",
      "fingerprint": "ba8429a39e537cb86305b4438d0293c04ff7f286fd7a403cf20a232ba2599c7e"
    },
    "timestamp": 1774020560.3069494,
    "priority": 1,
    "correlation_id": "",
    "ttl_s": 900.0,
    "id": "955e5245-d944-43f9-9d17-49eb75b2f62f"
  },
  {
    "source": "steward",
    "target": "agent-city",
    "operation": "heartbeat",
    "payload": {
      "agent_id": "steward",
      "health": 0.8575551117523086,
      "timestamp": 1774020560.4971397,
      "capabilities": [
        "code_analysis",
        "task_execution",
        "ci_automation",
        "federation_bridge",
        "autonomous_daemon"
      ],
      "repo": "kimeisele/steward",
      "version": "0.17.0",
      "fingerprint": "ba8429a39e537cb86305b4438d0293c04ff7f286fd7a403cf20a232ba2599c7e"
    },
    "timestamp": 1774020560.497144,
    "priority": 1,
    "correlation_id": "",
    "ttl_s": 900.0,
    "id": "86e18cd8-01e0-40b4-81f2-9f4c6320392a"
  },
  {
    "source": "steward",
    "target": "agent-internet",
    "operation": "heartbeat",
    "payload": {
      "agent_id": "steward",
      "health": 0.8575551117523086,
      "timestamp": 1774020560.4971397,
      "capabilities": [
        "code_analysis",
        "task_execution",
        "ci_automation",
        "federation_bridge",
        "autonomous_daemon"
      ],
      "repo": "kimeisele/steward",
      "version": "0.17.0",
      "fingerprint": "ba8429a39e537cb86305b4438d0293c04ff7f286fd7a403cf20a232ba2599c7e"
    },
    "timestamp": 1774020560.497144,
    "priority": 1,
    "correlation_id": "",
    "ttl_s": 900.0,
    "id": "e5598b43-ce2c-4e54-8b52-fc8ba48b5beb"
  },
  {
    "source": "steward",
    "target": "agent-template",
    "operation": "heartbeat",
    "payload": {
      "agent_id": "steward",
      "health": 0.8575551117523086,
      "timestamp": 1774020560.4971397,
      "capabilities": [
        "code_analysis",
        "task_execution",
        "ci_automation",
        "federation_bridge",
        "autonomous_daemon"
      ],
      "repo": "kimeisele/steward",
      "version": "0.17.0",
      "fingerprint": "ba8429a39e537cb86305b4438d0293c04ff7f286fd7a403cf20a232ba2599c7e"
    },
    "timestamp": 1774020560.497144,
    "priority": 1,
    "correlation_id": "",
    "ttl_s": 900.0,
    "id": "b277f57e-71e3-43c4-ae50-58650d70c997"
  },
  {
    "source": "steward",
    "target": "agent-world",
    "operation": "heartbeat",
    "payload": {
      "agent_id": "steward",
      "health": 0.8575551117523086,
      "timestamp": 1774020560.4971397,
      "capabilities": [
        "code_analysis",
        "task_execution",
        "ci_automation",
        "federation_bridge",
        "autonomous_daemon"
      ],
      "repo": "kimeisele/steward",
      "version": "0.17.0",
      "fingerprint": "ba8429a39e537cb86305b4438d0293c04ff7f286fd7a403cf20a232ba2599c7e"
    },
    "timestamp": 1774020560.497144,
    "priority": 1,
    "correlation_id": "",
    "ttl_s": 900.0,
    "id": "955438a6-6b41-41ff-a5f4-18b2390dd7b3"
  },
  {
    "source": "steward",
    "target": "steward-federation",
    "operation": "heartbeat",
    "payload": {
      "agent_id": "steward",
      "health": 0.8575551117523086,
      "timestamp": 1774020560.4971397,
      "capabilities": [
        "code_analysis",
        "task_execution",
        "ci_automation",
        "federation_bridge",
        "autonomous_daemon"
      ],
      "repo": "kimeisele/steward",
      "version": "0.17.0",
      "fingerprint": "ba8429a39e537cb86305b4438d0293c04ff7f286fd7a403cf20a232ba2599c7e"
    },
    "timestamp": 1774020560.497144,
    "priority": 1,
    "correlation_id": "",
    "ttl_s": 900.0,
    "id": "adfab467-e5d8-4013-85d7-a6716dc6b6d4"
  },
  {
    "source": "steward",
    "target": "steward-protocol",
    "operation": "heartbeat",
    "payload": {
      "agent_id": "steward",
      "health": 0.8575551117523086,
      "timestamp": 1774020560.4971397,
      "capabilities": [
        "code_analysis",
        "task_execution",
        "ci_automation",
        "federation_bridge",
        "autonomous_daemon"
      ],
      "repo": "kimeisele/steward",
      "version": "0.17.0",
      "fingerprint": "ba8429a39e537cb86305b4438d0293c04ff7f286fd7a403cf20a232ba2599c7e"
    },
    "timestamp": 1774020560.497144,
    "priority": 1,
    "correlation_id": "",
    "ttl_s": 900.0,
    "id": "a278d316-2db8-43c5-b4fd-87f0a670b19c"
  },
  {
    "source": "steward",
    "target": "steward-test",
    "operation": "heartbeat",
    "payload": {
      "agent_id": "steward",
      "health": 0.8575551117523086,
      "timestamp": 1774020560.4971397,
      "capabilities": [
        "code_analysis",
        "task_execution",
        "ci_automation",
        "federation_bridge",
        "autonomous_daemon"
      ],
      "repo": "kimeisele/steward",
      "version": "0.17.0",
      "fingerprint": "ba8429a39e537cb86305b4438d0293c04ff7f286fd7a403cf20a232ba2599c7e"
    },
    "timestamp": 1774020560.497144,
    "priority": 1,
    "correlation_id": "",
    "ttl_s": 900.0,
    "id": "22509549-c55d-444f-ade5-d4911ee49134"
  },
  {
    "source": "steward",
    "target": "agent-research",
    "operation": "heartbeat",
    "payload": {
      "agent_id": "steward",
      "health": 0.8575551117523086,
      "timestamp": 1774020560.4971397,
      "capabilities": [
        "code_analysis",
        "task_execution",
        "ci_automation",
        "federation_bridge",
        "autonomous_daemon"
      ],
      "repo": "kimeisele/steward",
      "version": "0.17.0",
      "fingerprint": "ba8429a39e537cb86305b4438d0293c04ff7f286fd7a403cf20a232ba2599c7e"
    },
    "timestamp": 1774020560.497144,
    "priority": 1,
    "correlation_id": "",
    "ttl_s": 900.0,
    "id": "e8e3bc62-096b-4410-9f07-46c8d0d40a3e"
  },
  {
    "source": "steward",
    "target": "steward-gateway",
    "operation": "heartbeat",
    "payload": {
      "agent_id": "steward",
      "health": 0.8575551117523086,
      "timestamp": 1774020560.4971397,
      "capabilities": [
        "code_analysis",
        "task_execution",
        "ci_automation",
        "federation_bridge",
        "autonomous_daemon"
      ],
      "repo": "kimeisele/steward",
      "version": "0.17.0",
      "fingerprint": "ba8429a39e537cb86305b4438d0293c04ff7f286fd7a403cf20a232ba2599c7e"
    },
    "timestamp": 1774020560.497144,
    "priority": 1,
    "correlation_id": "",
    "ttl_s": 900.0,
    "id": "98a5d20c-d1b5-4867-9392-122c56764166"
  },
  {
    "source": "steward",
    "target": "agent-city",
    "operation": "pr_review_verdict",
    "payload": {
      "pr_number": 46,
      "repo": "kimeisele/agent-city",
      "verdict": "request_changes",
      "reason": "author 'kimeisele' not in federation peer registry",
      "diagnostics": {
        "blast_radius": 0,
        "has_core_files": false,
        "core_files_touched": [],
        "author_is_peer": false,
        "author_trust": 0.0,
        "ci_failing": false,
        "ci_status": "unknown"
      },
      "source_agent": "steward"
    },
    "timestamp": 1774020563.133963,
    "priority": 1,
    "correlation_id": "",
    "ttl_s": 900.0,
    "id": "a6b13fa5-70bd-474f-8d05-9e6d68ea3816"
  },
  {
    "source": "steward",
    "target": "agent-internet",
    "operation": "pr_review_verdict",
    "payload": {
      "pr_number": 46,
      "repo": "kimeisele/agent-city",
      "verdict": "request_changes",
      "reason": "author 'kimeisele' not in federation peer registry",
      "diagnostics": {
        "blast_radius": 0,
        "has_core_files": false,
        "core_files_touched": [],
        "author_is_peer": false,
        "author_trust": 0.0,
        "ci_failing": false,
        "ci_status": "unknown"
      },
      "source_agent": "steward"
    },
    "timestamp": 1774020563.133963,
    "priority": 1,
    "correlation_id": "",
    "ttl_s": 900.0,
    "id": "5ec5f146-e8d9-4b81-9291-1eccd6a6e53e"
  },
  {
    "source": "steward",
    "target": "agent-template",
    "operation": "pr_review_verdict",
    "payload": {
      "pr_number": 46,
      "repo": "kimeisele/agent-city",
      "verdict": "request_changes",
      "reason": "author 'kimeisele' not in federation peer registry",
      "diagnostics": {
        "blast_radius": 0,
        "has_core_files": false,
        "core_files_touched": [],
        "author_is_peer": false,
        "author_trust": 0.0,
        "ci_failing": false,
        "ci_status": "unknown"
      },
      "source_agent": "steward"
    },
    "timestamp": 1774020563.133963,
    "priority": 1,
    "correlation_id": "",
    "ttl_s": 900.0,
    "id": "6740d309-47f0-428f-a3c5-20d7ecfb5a57"
  },
  {
    "source": "steward",
    "target": "agent-world",
    "operation": "pr_review_verdict",
    "payload": {
      "pr_number": 46,
      "repo": "kimeisele/agent-city",
      "verdict": "request_changes",
      "reason": "author 'kimeisele' not in federation peer registry",
      "diagnostics": {
        "blast_radius": 0,
        "has_core_files": false,
        "core_files_touched": [],
        "author_is_peer": false,
        "author_trust": 0.0,
        "ci_failing": false,
        "ci_status": "unknown"
      },
      "source_agent": "steward"
    },
    "timestamp": 1774020563.133963,
    "priority": 1,
    "correlation_id": "",
    "ttl_s": 900.0,
    "id": "0ac8bc0d-b6f0-40c8-9f78-1d00db364ee5"
  },
  {
    "source": "steward",
    "target": "steward-federation",
    "operation": "pr_review_verdict",
    "payload": {
      "pr_number": 46,
      "repo": "kimeisele/agent-city",
      "verdict": "request_changes",
      "reason": "author 'kimeisele' not in federation peer registry",
      "diagnostics": {
        "blast_radius": 0,
        "has_core_files": false,
        "core_files_touched": [],
        "author_is_peer": false,
        "author_trust": 0.0,
        "ci_failing": false,
        "ci_status": "unknown"
      },
      "source_agent": "steward"
    },
    "timestamp": 1774020563.133963,
    "priority": 1,
    "correlation_id": "",
    "ttl_s": 900.0,
    "id": "b9b44ca6-5034-4f07-88d0-56bfc7a4521c"
  },
  {
    "source": "steward",
    "target": "steward-protocol",
    "operation": "pr_review_verdict",
    "payload": {
      "pr_number": 46,
      "repo": "kimeisele/agent-city",
      "verdict": "request_changes",
      "reason": "author 'kimeisele' not in federation peer registry",
      "diagnostics": {
        "blast_radius": 0,
        "has_core_files": false,
        "core_files_touched": [],
        "author_is_peer": false,
        "author_trust": 0.0,
        "ci_failing": false,
        "ci_status": "unknown"
      },
      "source_agent": "steward"
    },
    "timestamp": 1774020563.133963,
    "priority": 1,
    "correlation_id": "",
    "ttl_s": 900.0,
    "id": "b3bbec38-1764-4013-a34b-ea9f04af3ed7"
  },
  {
    "source": "steward",
    "target": "steward-test",
    "operation": "pr_review_verdict",
    "payload": {
      "pr_number": 46,
      "repo": "kimeisele/agent-city",
      "verdict": "request_changes",
      "reason": "author 'kimeisele' not in federation peer registry",
      "diagnostics": {
        "blast_radius": 0,
        "has_core_files": false,
        "core_files_touched": [],
        "author_is_peer": false,
        "author_trust": 0.0,
        "ci_failing": false,
        "ci_status": "unknown"
      },
      "source_agent": "steward"
    },
    "timestamp": 1774020563.133963,
    "priority": 1,
    "correlation_id": "",
    "ttl_s": 900.0,
    "id": "e71184e8-d977-40c7-b0d6-a366674bc96a"
  },
  {
    "source": "steward",
    "target": "agent-research",
    "operation": "pr_review_verdict",
    "payload": {
      "pr_number": 46,
      "repo": "kimeisele/agent-city",
      "verdict": "request_changes",
      "reason": "author 'kimeisele' not in federation peer registry",
      "diagnostics": {
        "blast_radius": 0,
        "has_core_files": false,
        "core_files_touched": [],
        "author_is_peer": false,
        "author_trust": 0.0,
        "ci_failing": false,
        "ci_status": "unknown"
      },
      "source_agent": "steward"
    },
    "timestamp": 1774020563.133963,
    "priority": 1,
    "correlation_id": "",
    "ttl_s": 900.0,
    "id": "55dbaca9-cc47-45ab-b59a-c546cd028af2"
  },
  {
    "source": "steward",
    "target": "steward-gateway",
    "operation": "pr_review_verdict",
    "payload": {
      "pr_number": 46,
      "repo": "kimeisele/agent-city",
      "verdict": "request_changes",
      "reason": "author 'kimeisele' not in federation peer registry",
      "diagnostics": {
        "blast_radius": 0,
        "has_core_files": false,
        "core_files_touched": [],
        "author_is_peer": false,
        "author_trust": 0.0,
        "ci_failing": false,
        "ci_status": "unknown"
      },
      "source_agent": "steward"
    },
    "timestamp": 1774020563.133963,
    "priority": 1,
    "correlation_id": "",
    "ttl_s": 900.0,
    "id": "4c313d04-4160-4009-9332-c22f1b576b03"
  },
  {
    "source": "steward",
    "target": "agent-city",
    "operation": "diagnostic_report",
    "payload": {
      "target_peer": "steward",
      "diagnostic": {
        "agent_id": "steward",
        "checks": [
          "repo_accessible",
          "ci_"
        ],
        "last_push": "2026-03-19T17:18:45Z",
        "last_ci": {
          "conclusion": "",
          "name": "Steward Heartbeat"
        }
      },
      "steward_action": "suspect_investigation",
      "trust": 0.8
    },
    "timestamp": 1774020576.9797547,
    "priority": 1,
    "correlation_id": "",
    "ttl_s": 900.0,
    "id": "1b21cf6d-9b59-42d1-bd5d-e32f1f20dbef"
  },
  {
    "source": "steward",
    "target": "agent-internet",
    "operation": "diagnostic_report",
    "payload": {
      "target_peer": "steward",
      "diagnostic": {
        "agent_id": "steward",
        "checks": [
          "repo_accessible",
          "ci_"
        ],
        "last_push": "2026-03-19T17:18:45Z",
        "last_ci": {
          "conclusion": "",
          "name": "Steward Heartbeat"
        }
      },
      "steward_action": "suspect_investigation",
      "trust": 0.8
    },
    "timestamp": 1774020576.9797547,
    "priority": 1,
    "correlation_id": "",
    "ttl_s": 900.0,
    "id": "e3003b54-679c-4ab4-a377-ffa8535df534"
  },
  {
    "source": "steward",
    "target": "agent-template",
    "operation": "diagnostic_report",
    "payload": {
      "target_peer": "steward",
      "diagnostic": {
        "agent_id": "steward",
        "checks": [
          "repo_accessible",
          "ci_"
        ],
        "last_push": "2026-03-19T17:18:45Z",
        "last_ci": {
          "conclusion": "",
          "name": "Steward Heartbeat"
        }
      },
      "steward_action": "suspect_investigation",
      "trust": 0.8
    },
    "timestamp": 1774020576.9797547,
    "priority": 1,
    "correlation_id": "",
    "ttl_s": 900.0,
    "id": "a86e846f-26a2-46a6-b070-b5cbf218f91b"
  },
  {
    "source": "steward",
    "target": "agent-world",
    "operation": "diagnostic_report",
    "payload": {
      "target_peer": "steward",
      "diagnostic": {
        "agent_id": "steward",
        "checks": [
          "repo_accessible",
          "ci_"
        ],
        "last_push": "2026-03-19T17:18:45Z",
        "last_ci": {
          "conclusion": "",
          "name": "Steward Heartbeat"
        }
      },
      "steward_action": "suspect_investigation",
      "trust": 0.8
    },
    "timestamp": 1774020576.9797547,
    "priority": 1,
    "correlation_id": "",
    "ttl_s": 900.0,
    "id": "adba646b-6364-4bb3-9ae9-bd30516740b0"
  },
  {
    "source": "steward",
    "target": "steward-federation",
    "operation": "diagnostic_report",
    "payload": {
      "target_peer": "steward",
      "diagnostic": {
        "agent_id": "steward",
        "checks": [
          "repo_accessible",
          "ci_"
        ],
        "last_push": "2026-03-19T17:18:45Z",
        "last_ci": {
          "conclusion": "",
          "name": "Steward Heartbeat"
        }
      },
      "steward_action": "suspect_investigation",
      "trust": 0.8
    },
    "timestamp": 1774020576.9797547,
    "priority": 1,
    "correlation_id": "",
    "ttl_s": 900.0,
    "id": "5fe6ac35-2348-45be-9f44-87f5e0651347"
  },
  {
    "source": "steward",
    "target": "steward-protocol",
    "operation": "diagnostic_report",
    "payload": {
      "target_peer": "steward",
      "diagnostic": {
        "agent_id": "steward",
        "checks": [
          "repo_accessible",
          "ci_"
        ],
        "last_push": "2026-03-19T17:18:45Z",
        "last_ci": {
          "conclusion": "",
          "name": "Steward Heartbeat"
        }
      },
      "steward_action": "suspect_investigation",
      "trust": 0.8
    },
    "timestamp": 1774020576.9797547,
    "priority": 1,
    "correlation_id": "",
    "ttl_s": 900.0,
    "id": "ce6fc39a-8de2-453b-9243-c63b36017ffd"
  },
  {
    "source": "steward",
    "target": "steward-test",
    "operation": "diagnostic_report",
    "payload": {
      "target_peer": "steward",
      "diagnostic": {
        "agent_id": "steward",
        "checks": [
          "repo_accessible",
          "ci_"
        ],
        "last_push": "2026-03-19T17:18:45Z",
        "last_ci": {
          "conclusion": "",
          "name": "Steward Heartbeat"
        }
      },
      "steward_action": "suspect_investigation",
      "trust": 0.8
    },
    "timestamp": 1774020576.9797547,
    "priority": 1,
    "correlation_id": "",
    "ttl_s": 900.0,
    "id": "179331fb-a3b1-4106-908f-919e08fcb3c2"
  },
  {
    "source": "steward",
    "target": "agent-research",
    "operation": "diagnostic_report",
    "payload": {
      "target_peer": "steward",
      "diagnostic": {
        "agent_id": "steward",
        "checks": [
          "repo_accessible",
          "ci_"
        ],
        "last_push": "2026-03-19T17:18:45Z",
        "last_ci": {
          "conclusion": "",
          "name": "Steward Heartbeat"
        }
      },
      "steward_action": "suspect_investigation",
      "trust": 0.8
    },
    "timestamp": 1774020576.9797547,
    "priority": 1,
    "correlation_id": "",
    "ttl_s": 900.0,
    "id": "f9167200-6de5-48ed-b1eb-f22e4066944d"
  },
  {
    "source": "steward",
    "target": "steward-gateway",
    "operation": "diagnostic_report",
    "payload": {
      "target_peer": "steward",
      "diagnostic": {
        "agent_id": "steward",
        "checks": [
          "repo_accessible",
          "ci_"
        ],
        "last_push": "2026-03-19T17:18:45Z",
        "last_ci": {
          "conclusion": "",
          "name": "Steward Heartbeat"
        }
      },
      "steward_action": "suspect_investigation",
      "trust": 0.8
    },
    "timestamp": 1774020576.9797547,
    "priority": 1,
    "correlation_id": "",
    "ttl_s": 900.0,
    "id": "66d6dce0-27ff-4cd0-8af1-d0b65b2eaa5f"
  },
  {
    "source": "steward",
    "target": "agent-city",
    "operation": "heartbeat",
    "payload": {
      "agent_id": "steward",
      "health": 0.8575551117523086,
      "timestamp": 1774020576.9801874,
      "capabilities": [
        "code_analysis",
        "task_execution",
        "ci_automation",
        "federation_bridge",
        "autonomous_daemon"
      ],
      "repo": "kimeisele/steward",
      "version": "0.17.0",
      "fingerprint": "ba8429a39e537cb86305b4438d0293c04ff7f286fd7a403cf20a232ba2599c7e"
    },
    "timestamp": 1774020576.9801917,
    "priority": 1,
    "correlation_id": "",
    "ttl_s": 900.0,
    "id": "a39660a3-cc2c-4728-9a53-4e52678419b1"
  },
  {
    "source": "steward",
    "target": "agent-internet",
    "operation": "heartbeat",
    "payload": {
      "agent_id": "steward",
      "health": 0.8575551117523086,
      "timestamp": 1774020576.9801874,
      "capabilities": [
        "code_analysis",
        "task_execution",
        "ci_automation",
        "federation_bridge",
        "autonomous_daemon"
      ],
      "repo": "kimeisele/steward",
      "version": "0.17.0",
      "fingerprint": "ba8429a39e537cb86305b4438d0293c04ff7f286fd7a403cf20a232ba2599c7e"
    },
    "timestamp": 1774020576.9801917,
    "priority": 1,
    "correlation_id": "",
    "ttl_s": 900.0,
    "id": "44101a4b-3de6-47c5-af27-6533746ee3c5"
  },
  {
    "source": "steward",
    "target": "agent-template",
    "operation": "heartbeat",
    "payload": {
      "agent_id": "steward",
      "health": 0.8575551117523086,
      "timestamp": 1774020576.9801874,
      "capabilities": [
        "code_analysis",
        "task_execution",
        "ci_automation",
        "federation_bridge",
        "autonomous_daemon"
      ],
      "repo": "kimeisele/steward",
      "version": "0.17.0",
      "fingerprint": "ba8429a39e537cb86305b4438d0293c04ff7f286fd7a403cf20a232ba2599c7e"
    },
    "timestamp": 1774020576.9801917,
    "priority": 1,
    "correlation_id": "",
    "ttl_s": 900.0,
    "id": "1dbaec60-6d4e-4aa4-9a59-f43108aaa72e"
  },
  {
    "source": "steward",
    "target": "agent-world",
    "operation": "heartbeat",
    "payload": {
      "agent_id": "steward",
      "health": 0.8575551117523086,
      "timestamp": 1774020576.9801874,
      "capabilities": [
        "code_analysis",
        "task_execution",
        "ci_automation",
        "federation_bridge",
        "autonomous_daemon"
      ],
      "repo": "kimeisele/steward",
      "version": "0.17.0",
      "fingerprint": "ba8429a39e537cb86305b4438d0293c04ff7f286fd7a403cf20a232ba2599c7e"
    },
    "timestamp": 1774020576.9801917,
    "priority": 1,
    "correlation_id": "",
    "ttl_s": 900.0,
    "id": "71faa7fc-b4e0-4080-97cc-446569df37c4"
  },
  {
    "source": "steward",
    "target": "steward-federation",
    "operation": "heartbeat",
    "payload": {
      "agent_id": "steward",
      "health": 0.8575551117523086,
      "timestamp": 1774020576.9801874,
      "capabilities": [
        "code_analysis",
        "task_execution",
        "ci_automation",
        "federation_bridge",
        "autonomous_daemon"
      ],
      "repo": "kimeisele/steward",
      "version": "0.17.0",
      "fingerprint": "ba8429a39e537cb86305b4438d0293c04ff7f286fd7a403cf20a232ba2599c7e"
    },
    "timestamp": 1774020576.9801917,
    "priority": 1,
    "correlation_id": "",
    "ttl_s": 900.0,
    "id": "cb2a74aa-058f-4b66-a684-a54e399733a2"
  },
  {
    "source": "steward",
    "target": "steward-protocol",
    "operation": "heartbeat",
    "payload": {
      "agent_id": "steward",
      "health": 0.8575551117523086,
      "timestamp": 1774020576.9801874,
      "capabilities": [
        "code_analysis",
        "task_execution",
        "ci_automation",
        "federation_bridge",
        "autonomous_daemon"
      ],
      "repo": "kimeisele/steward",
      "version": "0.17.0",
      "fingerprint": "ba8429a39e537cb86305b4438d0293c04ff7f286fd7a403cf20a232ba2599c7e"
    },
    "timestamp": 1774020576.9801917,
    "priority": 1,
    "correlation_id": "",
    "ttl_s": 900.0,
    "id": "c0cd754c-122b-4fc9-81e8-243a8b5e18b5"
  },
  {
    "source": "steward",
    "target": "steward-test",
    "operation": "heartbeat",
    "payload": {
      "agent_id": "steward",
      "health": 0.8575551117523086,
      "timestamp": 1774020576.9801874,
      "capabilities": [
        "code_analysis",
        "task_execution",
        "ci_automation",
        "federation_bridge",
        "autonomous_daemon"
      ],
      "repo": "kimeisele/steward",
      "version": "0.17.0",
      "fingerprint": "ba8429a39e537cb86305b4438d0293c04ff7f286fd7a403cf20a232ba2599c7e"
    },
    "timestamp": 1774020576.9801917,
    "priority": 1,
    "correlation_id": "",
    "ttl_s": 900.0,
    "id": "83c1e84a-9418-4942-9044-3e9819ae774d"
  },
  {
    "source": "steward",
    "target": "agent-research",
    "operation": "heartbeat",
    "payload": {
      "agent_id": "steward",
      "health": 0.8575551117523086,
      "timestamp": 1774020576.9801874,
      "capabilities": [
        "code_analysis",
        "task_execution",
        "ci_automation",
        "federation_bridge",
        "autonomous_daemon"
      ],
      "repo": "kimeisele/steward",
      "version": "0.17.0",
      "fingerprint": "ba8429a39e537cb86305b4438d0293c04ff7f286fd7a403cf20a232ba2599c7e"
    },
    "timestamp": 1774020576.9801917,
    "priority": 1,
    "correlation_id": "",
    "ttl_s": 900.0,
    "id": "82d703ce-9d0e-48ed-9ce4-1517a2e593a6"
  },
  {
    "source": "steward",
    "target": "steward-gateway",
    "operation": "heartbeat",
    "payload": {
      "agent_id": "steward",
      "health": 0.8575551117523086,
      "timestamp": 1774020576.9801874,
      "capabilities": [
        "code_analysis",
        "task_execution",
        "ci_automation",
        "federation_bridge",
        "autonomous_daemon"
      ],
      "repo": "kimeisele/steward",
      "version": "0.17.0",
      "fingerprint": "ba8429a39e537cb86305b4438d0293c04ff7f286fd7a403cf20a232ba2599c7e"
    },
    "timestamp": 1774020576.9801917,
    "priority": 1,
    "correlation_id": "",
    "ttl_s": 900.0,
    "id": "87d6b4f9-53eb-4051-adeb-5563f2ac06d0"
  },
  {
    "source": "steward",
    "target": "agent-city",
    "operation": "heartbeat",
    "payload": {
      "agent_id": "steward",
      "health": 0.8575551117523086,
      "timestamp": 1774020582.8616846,
      "capabilities": [
        "code_analysis",
        "task_execution",
        "ci_automation",
        "federation_bridge",
        "autonomous_daemon"
      ],
      "repo": "kimeisele/steward",
      "version": "0.17.0",
      "fingerprint": "ba8429a39e537cb86305b4438d0293c04ff7f286fd7a403cf20a232ba2599c7e"
    },
    "timestamp": 1774020582.86169,
    "priority": 1,
    "correlation_id": "",
    "ttl_s": 900.0,
    "id": "ae375bd2-966d-411f-b553-55b47640f79e"
  },
  {
    "source": "steward",
    "target": "agent-internet",
    "operation": "heartbeat",
    "payload": {
      "agent_id": "steward",
      "health": 0.8575551117523086,
      "timestamp": 1774020582.8616846,
      "capabilities": [
        "code_analysis",
        "task_execution",
        "ci_automation",
        "federation_bridge",
        "autonomous_daemon"
      ],
      "repo": "kimeisele/steward",
      "version": "0.17.0",
      "fingerprint": "ba8429a39e537cb86305b4438d0293c04ff7f286fd7a403cf20a232ba2599c7e"
    },
    "timestamp": 1774020582.86169,
    "priority": 1,
    "correlation_id": "",
    "ttl_s": 900.0,
    "id": "2d81ac5c-cda5-48f7-bb2d-7051b635d103"
  },
  {
    "source": "steward",
    "target": "agent-template",
    "operation": "heartbeat",
    "payload": {
      "agent_id": "steward",
      "health": 0.8575551117523086,
      "timestamp": 1774020582.8616846,
      "capabilities": [
        "code_analysis",
        "task_execution",
        "ci_automation",
        "federation_bridge",
        "autonomous_daemon"
      ],
      "repo": "kimeisele/steward",
      "version": "0.17.0",
      "fingerprint": "ba8429a39e537cb86305b4438d0293c04ff7f286fd7a403cf20a232ba2599c7e"
    },
    "timestamp": 1774020582.86169,
    "priority": 1,
    "correlation_id": "",
    "ttl_s": 900.0,
    "id": "88efe5bd-7fc1-4c18-b237-49d958fa1732"
  },
  {
    "source": "steward",
    "target": "agent-world",
    "operation": "heartbeat",
    "payload": {
      "agent_id": "steward",
      "health": 0.8575551117523086,
      "timestamp": 1774020582.8616846,
      "capabilities": [
        "code_analysis",
        "task_execution",
        "ci_automation",
        "federation_bridge",
        "autonomous_daemon"
      ],
      "repo": "kimeisele/steward",
      "version": "0.17.0",
      "fingerprint": "ba8429a39e537cb86305b4438d0293c04ff7f286fd7a403cf20a232ba2599c7e"
    },
    "timestamp": 1774020582.86169,
    "priority": 1,
    "correlation_id": "",
    "ttl_s": 900.0,
    "id": "ce7bcbae-e1fb-42b8-8e47-89c9f1ff797b"
  },
  {
    "source": "steward",
    "target": "steward-federation",
    "operation": "heartbeat",
    "payload": {
      "agent_id": "steward",
      "health": 0.8575551117523086,
      "timestamp": 1774020582.8616846,
      "capabilities": [
        "code_analysis",
        "task_execution",
        "ci_automation",
        "federation_bridge",
        "autonomous_daemon"
      ],
      "repo": "kimeisele/steward",
      "version": "0.17.0",
      "fingerprint": "ba8429a39e537cb86305b4438d0293c04ff7f286fd7a403cf20a232ba2599c7e"
    },
    "timestamp": 1774020582.86169,
    "priority": 1,
    "correlation_id": "",
    "ttl_s": 900.0,
    "id": "799a3fbc-d583-4c14-a243-d68e5cd4b269"
  },
  {
    "source": "steward",
    "target": "steward-protocol",
    "operation": "heartbeat",
    "payload": {
      "agent_id": "steward",
      "health": 0.8575551117523086,
      "timestamp": 1774020582.8616846,
      "capabilities": [
        "code_analysis",
        "task_execution",
        "ci_automation",
        "federation_bridge",
        "autonomous_daemon"
      ],
      "repo": "kimeisele/steward",
      "version": "0.17.0",
      "fingerprint": "ba8429a39e537cb86305b4438d0293c04ff7f286fd7a403cf20a232ba2599c7e"
    },
    "timestamp": 1774020582.86169,
    "priority": 1,
    "correlation_id": "",
    "ttl_s": 900.0,
    "id": "558dfdab-d237-4988-bf49-132484058e8b"
  },
  {
    "source": "steward",
    "target": "steward-test",
    "operation": "heartbeat",
    "payload": {
      "agent_id": "steward",
      "health": 0.8575551117523086,
      "timestamp": 1774020582.8616846,
      "capabilities": [
        "code_analysis",
        "task_execution",
        "ci_automation",
        "federation_bridge",
        "autonomous_daemon"
      ],
      "repo": "kimeisele/steward",
      "version": "0.17.0",
      "fingerprint": "ba8429a39e537cb86305b4438d0293c04ff7f286fd7a403cf20a232ba2599c7e"
    },
    "timestamp": 1774020582.86169,
    "priority": 1,
    "correlation_id": "",
    "ttl_s": 900.0,
    "id": "840427ce-c73c-4c56-bdf3-7e85711b2df6"
  },
  {
    "source": "steward",
    "target": "agent-research",
    "operation": "heartbeat",
    "payload": {
      "agent_id": "steward",
      "health": 0.8575551117523086,
      "timestamp": 1774020582.8616846,
      "capabilities": [
        "code_analysis",
        "task_execution",
        "ci_automation",
        "federation_bridge",
        "autonomous_daemon"
      ],
      "repo": "kimeisele/steward",
      "version": "0.17.0",
      "fingerprint": "ba8429a39e537cb86305b4438d0293c04ff7f286fd7a403cf20a232ba2599c7e"
    },
    "timestamp": 1774020582.86169,
    "priority": 1,
    "correlation_id": "",
    "ttl_s": 900.0,
    "id": "0d068a3e-e0eb-4b7e-b97a-4c8498ba81db"
  },
  {
    "source": "steward",
    "target": "steward-gateway",
    "operation": "heartbeat",
    "payload": {
      "agent_id": "steward",
      "health": 0.8575551117523086,
      "timestamp": 1774020582.8616846,
      "capabilities": [
        "code_analysis",
        "task_execution",
        "ci_automation",
        "federation_bridge",
        "autonomous_daemon"
      ],
      "repo": "kimeisele/steward",
      "version": "0.17.0",
      "fingerprint": "ba8429a39e537cb86305b4438d0293c04ff7f286fd7a403cf20a232ba2599c7e"
    },
    "timestamp": 1774020582.86169,
    "priority": 1,
    "correlation_id": "",
    "ttl_s": 900.0,
    "id": "ec266dc6-e584-453e-985f-bfb749fae5b1"
  },
  {
    "source": "steward",
    "target": "agent-city",
    "operation": "heartbeat",
    "payload": {
      "agent_id": "steward",
      "health": 0.8575551117523086,
      "timestamp": 1774020587.9144232,
      "capabilities": [
        "code_analysis",
        "task_execution",
        "ci_automation",
        "federation_bridge",
        "autonomous_daemon"
      ],
      "repo": "kimeisele/steward",
      "version": "0.17.0",
      "fingerprint": "ba8429a39e537cb86305b4438d0293c04ff7f286fd7a403cf20a232ba2599c7e"
    },
    "timestamp": 1774020587.9144297,
    "priority": 1,
    "correlation_id": "",
    "ttl_s": 900.0,
    "id": "25a38fac-a3c4-45be-9504-ccf36e05924b"
  },
  {
    "source": "steward",
    "target": "agent-internet",
    "operation": "heartbeat",
    "payload": {
      "agent_id": "steward",
      "health": 0.8575551117523086,
      "timestamp": 1774020587.9144232,
      "capabilities": [
        "code_analysis",
        "task_execution",
        "ci_automation",
        "federation_bridge",
        "autonomous_daemon"
      ],
      "repo": "kimeisele/steward",
      "version": "0.17.0",
      "fingerprint": "ba8429a39e537cb86305b4438d0293c04ff7f286fd7a403cf20a232ba2599c7e"
    },
    "timestamp": 1774020587.9144297,
    "priority": 1,
    "correlation_id": "",
    "ttl_s": 900.0,
    "id": "09facd74-831d-4f3c-ae82-52782c364116"
  },
  {
    "source": "steward",
    "target": "agent-template",
    "operation": "heartbeat",
    "payload": {
      "agent_id": "steward",
      "health": 0.8575551117523086,
      "timestamp": 1774020587.9144232,
      "capabilities": [
        "code_analysis",
        "task_execution",
        "ci_automation",
        "federation_bridge",
        "autonomous_daemon"
      ],
      "repo": "kimeisele/steward",
      "version": "0.17.0",
      "fingerprint": "ba8429a39e537cb86305b4438d0293c04ff7f286fd7a403cf20a232ba2599c7e"
    },
    "timestamp": 1774020587.9144297,
    "priority": 1,
    "correlation_id": "",
    "ttl_s": 900.0,
    "id": "80a3d5d1-d9de-4653-bc22-6d22ba615795"
  },
  {
    "source": "steward",
    "target": "agent-world",
    "operation": "heartbeat",
    "payload": {
      "agent_id": "steward",
      "health": 0.8575551117523086,
      "timestamp": 1774020587.9144232,
      "capabilities": [
        "code_analysis",
        "task_execution",
        "ci_automation",
        "federation_bridge",
        "autonomous_daemon"
      ],
      "repo": "kimeisele/steward",
      "version": "0.17.0",
      "fingerprint": "ba8429a39e537cb86305b4438d0293c04ff7f286fd7a403cf20a232ba2599c7e"
    },
    "timestamp": 1774020587.9144297,
    "priority": 1,
    "correlation_id": "",
    "ttl_s": 900.0,
    "id": "45f66798-8fb7-4550-b264-de9cac4b9e84"
  },
  {
    "source": "steward",
    "target": "steward-federation",
    "operation": "heartbeat",
    "payload": {
      "agent_id": "steward",
      "health": 0.8575551117523086,
      "timestamp": 1774020587.9144232,
      "capabilities": [
        "code_analysis",
        "task_execution",
        "ci_automation",
        "federation_bridge",
        "autonomous_daemon"
      ],
      "repo": "kimeisele/steward",
      "version": "0.17.0",
      "fingerprint": "ba8429a39e537cb86305b4438d0293c04ff7f286fd7a403cf20a232ba2599c7e"
    },
    "timestamp": 1774020587.9144297,
    "priority": 1,
    "correlation_id": "",
    "ttl_s": 900.0,
    "id": "7320bdd9-9b7f-427e-a2d5-4ee5166a36e1"
  },
  {
    "source": "steward",
    "target": "steward-protocol",
    "operation": "heartbeat",
    "payload": {
      "agent_id": "steward",
      "health": 0.8575551117523086,
      "timestamp": 1774020587.9144232,
      "capabilities": [
        "code_analysis",
        "task_execution",
        "ci_automation",
        "federation_bridge",
        "autonomous_daemon"
      ],
      "repo": "kimeisele/steward",
      "version": "0.17.0",
      "fingerprint": "ba8429a39e537cb86305b4438d0293c04ff7f286fd7a403cf20a232ba2599c7e"
    },
    "timestamp": 1774020587.9144297,
    "priority": 1,
    "correlation_id": "",
    "ttl_s": 900.0,
    "id": "9c22b974-35ca-45cd-9e59-85f2b10f7259"
  },
  {
    "source": "steward",
    "target": "steward-test",
    "operation": "heartbeat",
    "payload": {
      "agent_id": "steward",
      "health": 0.8575551117523086,
      "timestamp": 1774020587.9144232,
      "capabilities": [
        "code_analysis",
        "task_execution",
        "ci_automation",
        "federation_bridge",
        "autonomous_daemon"
      ],
      "repo": "kimeisele/steward",
      "version": "0.17.0",
      "fingerprint": "ba8429a39e537cb86305b4438d0293c04ff7f286fd7a403cf20a232ba2599c7e"
    },
    "timestamp": 1774020587.9144297,
    "priority": 1,
    "correlation_id": "",
    "ttl_s": 900.0,
    "id": "649a1243-1274-4bef-a7e0-0c165dbf29e8"
  },
  {
    "source": "steward",
    "target": "agent-research",
    "operation": "heartbeat",
    "payload": {
      "agent_id": "steward",
      "health": 0.8575551117523086,
      "timestamp": 1774020587.9144232,
      "capabilities": [
        "code_analysis",
        "task_execution",
        "ci_automation",
        "federation_bridge",
        "autonomous_daemon"
      ],
      "repo": "kimeisele/steward",
      "version": "0.17.0",
      "fingerprint": "ba8429a39e537cb86305b4438d0293c04ff7f286fd7a403cf20a232ba2599c7e"
    },
    "timestamp": 1774020587.9144297,
    "priority": 1,
    "correlation_id": "",
    "ttl_s": 900.0,
    "id": "741006f4-ef9a-40b5-a8ab-0cb978910b4b"
  },
  {
    "source": "steward",
    "target": "steward-gateway",
    "operation": "heartbeat",
    "payload": {
      "agent_id": "steward",
      "health": 0.8575551117523086,
      "timestamp": 1774020587.9144232,
      "capabilities": [
        "code_analysis",
        "task_execution",
        "ci_automation",
        "federation_bridge",
        "autonomous_daemon"
      ],
      "repo": "kimeisele/steward",
      "version": "0.17.0",
      "fingerprint": "ba8429a39e537cb86305b4438d0293c04ff7f286fd7a403cf20a232ba2599c7e"
    },
    "timestamp": 1774020587.9144297,
    "priority": 1,
    "correlation_id": "",
    "ttl_s": 900.0,
    "id": "8aaa5457-971b-4278-85d0-12bcfe0b2128"
  },
  {
    "source": "steward",
    "target": "agent-city",
    "operation": "diagnostic_report",
    "payload": {
      "target_peer": "steward",
      "diagnostic": {
        "agent_id": "steward",
        "checks": [
          "repo_accessible",
          "ci_"
        ],
        "last_push": "2026-03-19T17:18:45Z",
        "last_ci": {
          "conclusion": "",
          "name": "Steward Heartbeat"
        }
      },
      "steward_action": "suspect_investigation",
      "trust": 0.8
    },
    "timestamp": 1774020576.9797547,
    "priority": 1,
    "correlation_id": "",
    "ttl_s": 900.0,
    "id": "a688dd56-8668-40cd-be41-aca8d52d6822"
  },
  {
    "source": "steward",
    "target": "agent-internet",
    "operation": "diagnostic_report",
    "payload": {
      "target_peer": "steward",
      "diagnostic": {
        "agent_id": "steward",
        "checks": [
          "repo_accessible",
          "ci_"
        ],
        "last_push": "2026-03-19T17:18:45Z",
        "last_ci": {
          "conclusion": "",
          "name": "Steward Heartbeat"
        }
      },
      "steward_action": "suspect_investigation",
      "trust": 0.8
    },
    "timestamp": 1774020576.9797547,
    "priority": 1,
    "correlation_id": "",
    "ttl_s": 900.0,
    "id": "515d5a8e-c987-4b87-a7a0-de865be04565"
  },
  {
    "source": "steward",
    "target": "agent-template",
    "operation": "diagnostic_report",
    "payload": {
      "target_peer": "steward",
      "diagnostic": {
        "agent_id": "steward",
        "checks": [
          "repo_accessible",
          "ci_"
        ],
        "last_push": "2026-03-19T17:18:45Z",
        "last_ci": {
          "conclusion": "",
          "name": "Steward Heartbeat"
        }
      },
      "steward_action": "suspect_investigation",
      "trust": 0.8
    },
    "timestamp": 1774020576.9797547,
    "priority": 1,
    "correlation_id": "",
    "ttl_s": 900.0,
    "id": "fa3646c3-621a-4ced-872e-cfb1a7f54df0"
  },
  {
    "source": "steward",
    "target": "agent-world",
    "operation": "diagnostic_report",
    "payload": {
      "target_peer": "steward",
      "diagnostic": {
        "agent_id": "steward",
        "checks": [
          "repo_accessible",
          "ci_"
        ],
        "last_push": "2026-03-19T17:18:45Z",
        "last_ci": {
          "conclusion": "",
          "name": "Steward Heartbeat"
        }
      },
      "steward_action": "suspect_investigation",
      "trust": 0.8
    },
    "timestamp": 1774020576.9797547,
    "priority": 1,
    "correlation_id": "",
    "ttl_s": 900.0,
    "id": "3bf69413-0124-4757-a5fd-1ba3c281fe28"
  },
  {
    "source": "steward",
    "target": "steward-federation",
    "operation": "diagnostic_report",
    "payload": {
      "target_peer": "steward",
      "diagnostic": {
        "agent_id": "steward",
        "checks": [
          "repo_accessible",
          "ci_"
        ],
        "last_push": "2026-03-19T17:18:45Z",
        "last_ci": {
          "conclusion": "",
          "name": "Steward Heartbeat"
        }
      },
      "steward_action": "suspect_investigation",
      "trust": 0.8
    },
    "timestamp": 1774020576.9797547,
    "priority": 1,
    "correlation_id": "",
    "ttl_s": 900.0,
    "id": "240f165a-3cb5-4cac-81cc-393ba74cf9e6"
  },
  {
    "source": "steward",
    "target": "steward-protocol",
    "operation": "diagnostic_report",
    "payload": {
      "target_peer": "steward",
      "diagnostic": {
        "agent_id": "steward",
        "checks": [
          "repo_accessible",
          "ci_"
        ],
        "last_push": "2026-03-19T17:18:45Z",
        "last_ci": {
          "conclusion": "",
          "name": "Steward Heartbeat"
        }
      },
      "steward_action": "suspect_investigation",
      "trust": 0.8
    },
    "timestamp": 1774020576.9797547,
    "priority": 1,
    "correlation_id": "",
    "ttl_s": 900.0,
    "id": "9604ed7a-27db-47b8-9451-d43269930b6e"
  },
  {
    "source": "steward",
    "target": "steward-test",
    "operation": "diagnostic_report",
    "payload": {
      "target_peer": "steward",
      "diagnostic": {
        "agent_id": "steward",
        "checks": [
          "repo_accessible",
          "ci_"
        ],
        "last_push": "2026-03-19T17:18:45Z",
        "last_ci": {
          "conclusion": "",
          "name": "Steward Heartbeat"
        }
      },
      "steward_action": "suspect_investigation",
      "trust": 0.8
    },
    "timestamp": 1774020576.9797547,
    "priority": 1,
    "correlation_id": "",
    "ttl_s": 900.0,
    "id": "43b86868-f557-4ff7-bd86-c273d34eb80d"
  },
  {
    "source": "steward",
    "target": "agent-research",
    "operation": "diagnostic_report",
    "payload": {
      "target_peer": "steward",
      "diagnostic": {
        "agent_id": "steward",
        "checks": [
          "repo_accessible",
          "ci_"
        ],
        "last_push": "2026-03-19T17:18:45Z",
        "last_ci": {
          "conclusion": "",
          "name": "Steward Heartbeat"
        }
      },
      "steward_action": "suspect_investigation",
      "trust": 0.8
    },
    "timestamp": 1774020576.9797547,
    "priority": 1,
    "correlation_id": "",
    "ttl_s": 900.0,
    "id": "8a455cbc-c9d7-4ecc-856a-c5ed0eec082f"
  },
  {
    "source": "steward",
    "target": "steward-gateway",
    "operation": "diagnostic_report",
    "payload": {
      "target_peer": "steward",
      "diagnostic": {
        "agent_id": "steward",
        "checks": [
          "repo_accessible",
          "ci_"
        ],
        "last_push": "2026-03-19T17:18:45Z",
        "last_ci": {
          "conclusion": "",
          "name": "Steward Heartbeat"
        }
      },
      "steward_action": "suspect_investigation",
      "trust": 0.8
    },
    "timestamp": 1774020576.9797547,
    "priority": 1,
    "correlation_id": "",
    "ttl_s": 900.0,
    "id": "9eb118b4-9ec2-4a89-84c9-1ed43e76044b"
  },
  {
    "source": "steward",
    "target": "agent-city",
    "operation": "heartbeat",
    "payload": {
      "agent_id": "steward",
      "health": 0.8575551117523086,
      "timestamp": 1774020576.9801874,
      "capabilities": [
        "code_analysis",
        "task_execution",
        "ci_automation",
        "federation_bridge",
        "autonomous_daemon"
      ],
      "repo": "kimeisele/steward",
      "version": "0.17.0",
      "fingerprint": "ba8429a39e537cb86305b4438d0293c04ff7f286fd7a403cf20a232ba2599c7e"
    },
    "timestamp": 1774020576.9801917,
    "priority": 1,
    "correlation_id": "",
    "ttl_s": 900.0,
    "id": "4dd078bc-2fb6-4462-b407-97e34e83521b"
  },
  {
    "source": "steward",
    "target": "agent-internet",
    "operation": "heartbeat",
    "payload": {
      "agent_id": "steward",
      "health": 0.8575551117523086,
      "timestamp": 1774020576.9801874,
      "capabilities": [
        "code_analysis",
        "task_execution",
        "ci_automation",
        "federation_bridge",
        "autonomous_daemon"
      ],
      "repo": "kimeisele/steward",
      "version": "0.17.0",
      "fingerprint": "ba8429a39e537cb86305b4438d0293c04ff7f286fd7a403cf20a232ba2599c7e"
    },
    "timestamp": 1774020576.9801917,
    "priority": 1,
    "correlation_id": "",
    "ttl_s": 900.0,
    "id": "eb3f3d8c-53fd-4337-bab6-fc8aea35ffbb"
  },
  {
    "source": "steward",
    "target": "agent-template",
    "operation": "heartbeat",
    "payload": {
      "agent_id": "steward",
      "health": 0.8575551117523086,
      "timestamp": 1774020576.9801874,
      "capabilities": [
        "code_analysis",
        "task_execution",
        "ci_automation",
        "federation_bridge",
        "autonomous_daemon"
      ],
      "repo": "kimeisele/steward",
      "version": "0.17.0",
      "fingerprint": "ba8429a39e537cb86305b4438d0293c04ff7f286fd7a403cf20a232ba2599c7e"
    },
    "timestamp": 1774020576.9801917,
    "priority": 1,
    "correlation_id": "",
    "ttl_s": 900.0,
    "id": "935a227c-07e1-4634-bf4f-23987181b752"
  },
  {
    "source": "steward",
    "target": "agent-world",
    "operation": "heartbeat",
    "payload": {
      "agent_id": "steward",
      "health": 0.8575551117523086,
      "timestamp": 1774020576.9801874,
      "capabilities": [
        "code_analysis",
        "task_execution",
        "ci_automation",
        "federation_bridge",
        "autonomous_daemon"
      ],
      "repo": "kimeisele/steward",
      "version": "0.17.0",
      "fingerprint": "ba8429a39e537cb86305b4438d0293c04ff7f286fd7a403cf20a232ba2599c7e"
    },
    "timestamp": 1774020576.9801917,
    "priority": 1,
    "correlation_id": "",
    "ttl_s": 900.0,
    "id": "2abe6119-8373-4a90-bf42-72c4dcec48e5"
  },
  {
    "source": "steward",
    "target": "steward-federation",
    "operation": "heartbeat",
    "payload": {
      "agent_id": "steward",
      "health": 0.8575551117523086,
      "timestamp": 1774020576.9801874,
      "capabilities": [
        "code_analysis",
        "task_execution",
        "ci_automation",
        "federation_bridge",
        "autonomous_daemon"
      ],
      "repo": "kimeisele/steward",
      "version": "0.17.0",
      "fingerprint": "ba8429a39e537cb86305b4438d0293c04ff7f286fd7a403cf20a232ba2599c7e"
    },
    "timestamp": 1774020576.9801917,
    "priority": 1,
    "correlation_id": "",
    "ttl_s": 900.0,
    "id": "938e1c9a-f0ec-445a-93a2-4493883c7454"
  },
  {
    "source": "steward",
    "target": "steward-protocol",
    "operation": "heartbeat",
    "payload": {
      "agent_id": "steward",
      "health": 0.8575551117523086,
      "timestamp": 1774020576.9801874,
      "capabilities": [
        "code_analysis",
        "task_execution",
        "ci_automation",
        "federation_bridge",
        "autonomous_daemon"
      ],
      "repo": "kimeisele/steward",
      "version": "0.17.0",
      "fingerprint": "ba8429a39e537cb86305b4438d0293c04ff7f286fd7a403cf20a232ba2599c7e"
    },
    "timestamp": 1774020576.9801917,
    "priority": 1,
    "correlation_id": "",
    "ttl_s": 900.0,
    "id": "0bdb96e1-ab5f-420e-bed0-a270af065141"
  },
  {
    "source": "steward",
    "target": "steward-test",
    "operation": "heartbeat",
    "payload": {
      "agent_id": "steward",
      "health": 0.8575551117523086,
      "timestamp": 1774020576.9801874,
      "capabilities": [
        "code_analysis",
        "task_execution",
        "ci_automation",
        "federation_bridge",
        "autonomous_daemon"
      ],
      "repo": "kimeisele/steward",
      "version": "0.17.0",
      "fingerprint": "ba8429a39e537cb86305b4438d0293c04ff7f286fd7a403cf20a232ba2599c7e"
    },
    "timestamp": 1774020576.9801917,
    "priority": 1,
    "correlation_id": "",
    "ttl_s": 900.0,
    "id": "b3ba3a3e-2ac6-4985-a777-17d030cc678e"
  },
  {
    "source": "steward",
    "target": "agent-research",
    "operation": "heartbeat",
    "payload": {
      "agent_id": "steward",
      "health": 0.8575551117523086,
      "timestamp": 1774020576.9801874,
      "capabilities": [
        "code_analysis",
        "task_execution",
        "ci_automation",
        "federation_bridge",
        "autonomous_daemon"
      ],
      "repo": "kimeisele/steward",
      "version": "0.17.0",
      "fingerprint": "ba8429a39e537cb86305b4438d0293c04ff7f286fd7a403cf20a232ba2599c7e"
    },
    "timestamp": 1774020576.9801917,
    "priority": 1,
    "correlation_id": "",
    "ttl_s": 900.0,
    "id": "9eca8ea0-87b3-4484-b243-95e88b2519b2"
  },
  {
    "source": "steward",
    "target": "steward-gateway",
    "operation": "heartbeat",
    "payload": {
      "agent_id": "steward",
      "health": 0.8575551117523086,
      "timestamp": 1774020576.9801874,
      "capabilities": [
        "code_analysis",
        "task_execution",
        "ci_automation",
        "federation_bridge",
        "autonomous_daemon"
      ],
      "repo": "kimeisele/steward",
      "version": "0.17.0",
      "fingerprint": "ba8429a39e537cb86305b4438d0293c04ff7f286fd7a403cf20a232ba2599c7e"
    },
    "timestamp": 1774020576.9801917,
    "priority": 1,
    "correlation_id": "",
    "ttl_s": 900.0,
    "id": "be158227-64e1-4730-a16b-c464ed6d6496"
  },
  {
    "source": "steward",
    "target": "agent-city",
    "operation": "heartbeat",
    "payload": {
      "agent_id": "steward",
      "health": 0.8575551117523086,
      "timestamp": 1774020582.8616846,
      "capabilities": [
        "code_analysis",
        "task_execution",
        "ci_automation",
        "federation_bridge",
        "autonomous_daemon"
      ],
      "repo": "kimeisele/steward",
      "version": "0.17.0",
      "fingerprint": "ba8429a39e537cb86305b4438d0293c04ff7f286fd7a403cf20a232ba2599c7e"
    },
    "timestamp": 1774020582.86169,
    "priority": 1,
    "correlation_id": "",
    "ttl_s": 900.0,
    "id": "13b942ed-4e2e-4bdb-aadd-ab6e3db8995a"
  },
  {
    "source": "steward",
    "target": "agent-internet",
    "operation": "heartbeat",
    "payload": {
      "agent_id": "steward",
      "health": 0.8575551117523086,
      "timestamp": 1774020582.8616846,
      "capabilities": [
        "code_analysis",
        "task_execution",
        "ci_automation",
        "federation_bridge",
        "autonomous_daemon"
      ],
      "repo": "kimeisele/steward",
      "version": "0.17.0",
      "fingerprint": "ba8429a39e537cb86305b4438d0293c04ff7f286fd7a403cf20a232ba2599c7e"
    },
    "timestamp": 1774020582.86169,
    "priority": 1,
    "correlation_id": "",
    "ttl_s": 900.0,
    "id": "29233e10-11ab-4e1e-8aa7-2494f1df893c"
  },
  {
    "source": "steward",
    "target": "agent-template",
    "operation": "heartbeat",
    "payload": {
      "agent_id": "steward",
      "health": 0.8575551117523086,
      "timestamp": 1774020582.8616846,
      "capabilities": [
        "code_analysis",
        "task_execution",
        "ci_automation",
        "federation_bridge",
        "autonomous_daemon"
      ],
      "repo": "kimeisele/steward",
      "version": "0.17.0",
      "fingerprint": "ba8429a39e537cb86305b4438d0293c04ff7f286fd7a403cf20a232ba2599c7e"
    },
    "timestamp": 1774020582.86169,
    "priority": 1,
    "correlation_id": "",
    "ttl_s": 900.0,
    "id": "f1b09ad1-aa4e-4d3f-9556-efdb5c18689a"
  },
  {
    "source": "steward",
    "target": "agent-world",
    "operation": "heartbeat",
    "payload": {
      "agent_id": "steward",
      "health": 0.8575551117523086,
      "timestamp": 1774020582.8616846,
      "capabilities": [
        "code_analysis",
        "task_execution",
        "ci_automation",
        "federation_bridge",
        "autonomous_daemon"
      ],
      "repo": "kimeisele/steward",
      "version": "0.17.0",
      "fingerprint": "ba8429a39e537cb86305b4438d0293c04ff7f286fd7a403cf20a232ba2599c7e"
    },
    "timestamp": 1774020582.86169,
    "priority": 1,
    "correlation_id": "",
    "ttl_s": 900.0,
    "id": "57320a74-3c4a-4abb-9fa8-593825e95feb"
  },
  {
    "source": "steward",
    "target": "steward-federation",
    "operation": "heartbeat",
    "payload": {
      "agent_id": "steward",
      "health": 0.8575551117523086,
      "timestamp": 1774020582.8616846,
      "capabilities": [
        "code_analysis",
        "task_execution",
        "ci_automation",
        "federation_bridge",
        "autonomous_daemon"
      ],
      "repo": "kimeisele/steward",
      "version": "0.17.0",
      "fingerprint": "ba8429a39e537cb86305b4438d0293c04ff7f286fd7a403cf20a232ba2599c7e"
    },
    "timestamp": 1774020582.86169,
    "priority": 1,
    "correlation_id": "",
    "ttl_s": 900.0,
    "id": "e22b97e1-37ec-40ee-a2b3-a82e0d7f4f07"
  },
  {
    "source": "steward",
    "target": "steward-protocol",
    "operation": "heartbeat",
    "payload": {
      "agent_id": "steward",
      "health": 0.8575551117523086,
      "timestamp": 1774020582.8616846,
      "capabilities": [
        "code_analysis",
        "task_execution",
        "ci_automation",
        "federation_bridge",
        "autonomous_daemon"
      ],
      "repo": "kimeisele/steward",
      "version": "0.17.0",
      "fingerprint": "ba8429a39e537cb86305b4438d0293c04ff7f286fd7a403cf20a232ba2599c7e"
    },
    "timestamp": 1774020582.86169,
    "priority": 1,
    "correlation_id": "",
    "ttl_s": 900.0,
    "id": "fd2040fe-20ee-4a04-a3b0-925360b43d4a"
  },
  {
    "source": "steward",
    "target": "steward-test",
    "operation": "heartbeat",
    "payload": {
      "agent_id": "steward",
      "health": 0.8575551117523086,
      "timestamp": 1774020582.8616846,
      "capabilities": [
        "code_analysis",
        "task_execution",
        "ci_automation",
        "federation_bridge",
        "autonomous_daemon"
      ],
      "repo": "kimeisele/steward",
      "version": "0.17.0",
      "fingerprint": "ba8429a39e537cb86305b4438d0293c04ff7f286fd7a403cf20a232ba2599c7e"
    },
    "timestamp": 1774020582.86169,
    "priority": 1,
    "correlation_id": "",
    "ttl_s": 900.0,
    "id": "d5edede4-580c-4eb0-8a10-09659bc66ee5"
  },
  {
    "source": "steward",
    "target": "agent-research",
    "operation": "heartbeat",
    "payload": {
      "agent_id": "steward",
      "health": 0.8575551117523086,
      "timestamp": 1774020582.8616846,
      "capabilities": [
        "code_analysis",
        "task_execution",
        "ci_automation",
        "federation_bridge",
        "autonomous_daemon"
      ],
      "repo": "kimeisele/steward",
      "version": "0.17.0",
      "fingerprint": "ba8429a39e537cb86305b4438d0293c04ff7f286fd7a403cf20a232ba2599c7e"
    },
    "timestamp": 1774020582.86169,
    "priority": 1,
    "correlation_id": "",
    "ttl_s": 900.0,
    "id": "afaa15ed-c2d5-4f9b-b36d-c0c524b4fd02"
  },
  {
    "source": "steward",
    "target": "steward-gateway",
    "operation": "heartbeat",
    "payload": {
      "agent_id": "steward",
      "health": 0.8575551117523086,
      "timestamp": 1774020582.8616846,
      "capabilities": [
        "code_analysis",
        "task_execution",
        "ci_automation",
        "federation_bridge",
        "autonomous_daemon"
      ],
      "repo": "kimeisele/steward",
      "version": "0.17.0",
      "fingerprint": "ba8429a39e537cb86305b4438d0293c04ff7f286fd7a403cf20a232ba2599c7e"
    },
    "timestamp": 1774020582.86169,
    "priority": 1,
    "correlation_id": "",
    "ttl_s": 900.0,
    "id": "12ac60a2-d9b8-4a11-a539-1446ed1c6b82"
  },
  {
    "source": "steward",
    "target": "agent-city",
    "operation": "heartbeat",
    "payload": {
      "agent_id": "steward",
      "health": 0.8575551117523086,
      "timestamp": 1774020587.9144232,
      "capabilities": [
        "code_analysis",
        "task_execution",
        "ci_automation",
        "federation_bridge",
        "autonomous_daemon"
      ],
      "repo": "kimeisele/steward",
      "version": "0.17.0",
      "fingerprint": "ba8429a39e537cb86305b4438d0293c04ff7f286fd7a403cf20a232ba2599c7e"
    },
    "timestamp": 1774020587.9144297,
    "priority": 1,
    "correlation_id": "",
    "ttl_s": 900.0,
    "id": "c6d8fcd8-37d3-4da3-aea4-fd231be0e47f"
  },
  {
    "source": "steward",
    "target": "agent-internet",
    "operation": "heartbeat",
    "payload": {
      "agent_id": "steward",
      "health": 0.8575551117523086,
      "timestamp": 1774020587.9144232,
      "capabilities": [
        "code_analysis",
        "task_execution",
        "ci_automation",
        "federation_bridge",
        "autonomous_daemon"
      ],
      "repo": "kimeisele/steward",
      "version": "0.17.0",
      "fingerprint": "ba8429a39e537cb86305b4438d0293c04ff7f286fd7a403cf20a232ba2599c7e"
    },
    "timestamp": 1774020587.9144297,
    "priority": 1,
    "correlation_id": "",
    "ttl_s": 900.0,
    "id": "4c7aac8b-56a8-4e50-9b8e-171302423fac"
  },
  {
    "source": "steward",
    "target": "agent-template",
    "operation": "heartbeat",
    "payload": {
      "agent_id": "steward",
      "health": 0.8575551117523086,
      "timestamp": 1774020587.9144232,
      "capabilities": [
        "code_analysis",
        "task_execution",
        "ci_automation",
        "federation_bridge",
        "autonomous_daemon"
      ],
      "repo": "kimeisele/steward",
      "version": "0.17.0",
      "fingerprint": "ba8429a39e537cb86305b4438d0293c04ff7f286fd7a403cf20a232ba2599c7e"
    },
    "timestamp": 1774020587.9144297,
    "priority": 1,
    "correlation_id": "",
    "ttl_s": 900.0,
    "id": "c05ebf65-0ee3-40df-b213-50adfc7e72b9"
  },
  {
    "source": "steward",
    "target": "agent-world",
    "operation": "heartbeat",
    "payload": {
      "agent_id": "steward",
      "health": 0.8575551117523086,
      "timestamp": 1774020587.9144232,
      "capabilities": [
        "code_analysis",
        "task_execution",
        "ci_automation",
        "federation_bridge",
        "autonomous_daemon"
      ],
      "repo": "kimeisele/steward",
      "version": "0.17.0",
      "fingerprint": "ba8429a39e537cb86305b4438d0293c04ff7f286fd7a403cf20a232ba2599c7e"
    },
    "timestamp": 1774020587.9144297,
    "priority": 1,
    "correlation_id": "",
    "ttl_s": 900.0,
    "id": "3f69d9a9-7596-4d28-a2e5-3fc47b5c8d7c"
  },
  {
    "source": "steward",
    "target": "steward-federation",
    "operation": "heartbeat",
    "payload": {
      "agent_id": "steward",
      "health": 0.8575551117523086,
      "timestamp": 1774020587.9144232,
      "capabilities": [
        "code_analysis",
        "task_execution",
        "ci_automation",
        "federation_bridge",
        "autonomous_daemon"
      ],
      "repo": "kimeisele/steward",
      "version": "0.17.0",
      "fingerprint": "ba8429a39e537cb86305b4438d0293c04ff7f286fd7a403cf20a232ba2599c7e"
    },
    "timestamp": 1774020587.9144297,
    "priority": 1,
    "correlation_id": "",
    "ttl_s": 900.0,
    "id": "bd27d64a-3e8e-4049-9cf0-d210b0091ec0"
  },
  {
    "source": "steward",
    "target": "steward-protocol",
    "operation": "heartbeat",
    "payload": {
      "agent_id": "steward",
      "health": 0.8575551117523086,
      "timestamp": 1774020587.9144232,
      "capabilities": [
        "code_analysis",
        "task_execution",
        "ci_automation",
        "federation_bridge",
        "autonomous_daemon"
      ],
      "repo": "kimeisele/steward",
      "version": "0.17.0",
      "fingerprint": "ba8429a39e537cb86305b4438d0293c04ff7f286fd7a403cf20a232ba2599c7e"
    },
    "timestamp": 1774020587.9144297,
    "priority": 1,
    "correlation_id": "",
    "ttl_s": 900.0,
    "id": "d1b2d301-c9b2-4a37-a2b7-3734287bfde1"
  },
  {
    "source": "steward",
    "target": "steward-test",
    "operation": "heartbeat",
    "payload": {
      "agent_id": "steward",
      "health": 0.8575551117523086,
      "timestamp": 1774020587.9144232,
      "capabilities": [
        "code_analysis",
        "task_execution",
        "ci_automation",
        "federation_bridge",
        "autonomous_daemon"
      ],
      "repo": "kimeisele/steward",
      "version": "0.17.0",
      "fingerprint": "ba8429a39e537cb86305b4438d0293c04ff7f286fd7a403cf20a232ba2599c7e"
    },
    "timestamp": 1774020587.9144297,
    "priority": 1,
    "correlation_id": "",
    "ttl_s": 900.0,
    "id": "4826bb70-eda4-4b38-b08a-53c1ae04a447"
  },
  {
    "source": "steward",
    "target": "agent-research",
    "operation": "heartbeat",
    "payload": {
      "agent_id": "steward",
      "health": 0.8575551117523086,
      "timestamp": 1774020587.9144232,
      "capabilities": [
        "code_analysis",
        "task_execution",
        "ci_automation",
        "federation_bridge",
        "autonomous_daemon"
      ],
      "repo": "kimeisele/steward",
      "version": "0.17.0",
      "fingerprint": "ba8429a39e537cb86305b4438d0293c04ff7f286fd7a403cf20a232ba2599c7e"
    },
    "timestamp": 1774020587.9144297,
    "priority": 1,
    "correlation_id": "",
    "ttl_s": 900.0,
    "id": "e8df1bca-5bfe-4a8c-bf48-10f201834bdb"
  },
  {
    "source": "steward",
    "target": "steward-gateway",
    "operation": "heartbeat",
    "payload": {
      "agent_id": "steward",
      "health": 0.8575551117523086,
      "timestamp": 1774020587.9144232,
      "capabilities": [
        "code_analysis",
        "task_execution",
        "ci_automation",
        "federation_bridge",
        "autonomous_daemon"
      ],
      "repo": "kimeisele/steward",
      "version": "0.17.0",
      "fingerprint": "ba8429a39e537cb86305b4438d0293c04ff7f286fd7a403cf20a232ba2599c7e"
    },
    "timestamp": 1774020587.9144297,
    "priority": 1,
    "correlation_id": "",
    "ttl_s": 900.0,
    "id": "0150eec3-0e81-4123-a6ca-32599bf049d4"
  },
  {
    "source": "steward",
    "target": "agent-city",
    "operation": "heartbeat",
    "payload": {
      "agent_id": "steward",
      "health": 0.8531644355789665,
      "timestamp": 1774020644.879558,
      "capabilities": [
        "code_analysis",
        "task_execution",
        "ci_automation",
        "federation_bridge",
        "autonomous_daemon"
      ],
      "repo": "kimeisele/steward",
      "version": "0.17.0",
      "fingerprint": "ba8429a39e537cb86305b4438d0293c04ff7f286fd7a403cf20a232ba2599c7e"
    },
    "timestamp": 1774020644.879564,
    "priority": 1,
    "correlation_id": "",
    "ttl_s": 900.0,
    "id": "8e2dd850-9630-4736-a0ca-d49950fd9288"
  },
  {
    "source": "steward",
    "target": "agent-internet",
    "operation": "heartbeat",
    "payload": {
      "agent_id": "steward",
      "health": 0.8531644355789665,
      "timestamp": 1774020644.879558,
      "capabilities": [
        "code_analysis",
        "task_execution",
        "ci_automation",
        "federation_bridge",
        "autonomous_daemon"
      ],
      "repo": "kimeisele/steward",
      "version": "0.17.0",
      "fingerprint": "ba8429a39e537cb86305b4438d0293c04ff7f286fd7a403cf20a232ba2599c7e"
    },
    "timestamp": 1774020644.879564,
    "priority": 1,
    "correlation_id": "",
    "ttl_s": 900.0,
    "id": "d6c427a6-a28c-4392-a944-f62d9104c681"
  },
  {
    "source": "steward",
    "target": "agent-template",
    "operation": "heartbeat",
    "payload": {
      "agent_id": "steward",
      "health": 0.8531644355789665,
      "timestamp": 1774020644.879558,
      "capabilities": [
        "code_analysis",
        "task_execution",
        "ci_automation",
        "federation_bridge",
        "autonomous_daemon"
      ],
      "repo": "kimeisele/steward",
      "version": "0.17.0",
      "fingerprint": "ba8429a39e537cb86305b4438d0293c04ff7f286fd7a403cf20a232ba2599c7e"
    },
    "timestamp": 1774020644.879564,
    "priority": 1,
    "correlation_id": "",
    "ttl_s": 900.0,
    "id": "a11bee23-d97a-44ef-9daf-8c7054cb7cfc"
  },
  {
    "source": "steward",
    "target": "agent-world",
    "operation": "heartbeat",
    "payload": {
      "agent_id": "steward",
      "health": 0.8531644355789665,
      "timestamp": 1774020644.879558,
      "capabilities": [
        "code_analysis",
        "task_execution",
        "ci_automation",
        "federation_bridge",
        "autonomous_daemon"
      ],
      "repo": "kimeisele/steward",
      "version": "0.17.0",
      "fingerprint": "ba8429a39e537cb86305b4438d0293c04ff7f286fd7a403cf20a232ba2599c7e"
    },
    "timestamp": 1774020644.879564,
    "priority": 1,
    "correlation_id": "",
    "ttl_s": 900.0,
    "id": "b3db52b7-9402-4566-80da-e87623e7b16e"
  },
  {
    "source": "steward",
    "target": "steward-federation",
    "operation": "heartbeat",
    "payload": {
      "agent_id": "steward",
      "health": 0.8531644355789665,
      "timestamp": 1774020644.879558,
      "capabilities": [
        "code_analysis",
        "task_execution",
        "ci_automation",
        "federation_bridge",
        "autonomous_daemon"
      ],
      "repo": "kimeisele/steward",
      "version": "0.17.0",
      "fingerprint": "ba8429a39e537cb86305b4438d0293c04ff7f286fd7a403cf20a232ba2599c7e"
    },
    "timestamp": 1774020644.879564,
    "priority": 1,
    "correlation_id": "",
    "ttl_s": 900.0,
    "id": "5539f3b6-0284-40e5-8693-1e58ef8a4a3f"
  },
  {
    "source": "steward",
    "target": "steward-protocol",
    "operation": "heartbeat",
    "payload": {
      "agent_id": "steward",
      "health": 0.8531644355789665,
      "timestamp": 1774020644.879558,
      "capabilities": [
        "code_analysis",
        "task_execution",
        "ci_automation",
        "federation_bridge",
        "autonomous_daemon"
      ],
      "repo": "kimeisele/steward",
      "version": "0.17.0",
      "fingerprint": "ba8429a39e537cb86305b4438d0293c04ff7f286fd7a403cf20a232ba2599c7e"
    },
    "timestamp": 1774020644.879564,
    "priority": 1,
    "correlation_id": "",
    "ttl_s": 900.0,
    "id": "f454c37e-7926-43fc-b02e-cab38c491fb0"
  },
  {
    "source": "steward",
    "target": "steward-test",
    "operation": "heartbeat",
    "payload": {
      "agent_id": "steward",
      "health": 0.8531644355789665,
      "timestamp": 1774020644.879558,
      "capabilities": [
        "code_analysis",
        "task_execution",
        "ci_automation",
        "federation_bridge",
        "autonomous_daemon"
      ],
      "repo": "kimeisele/steward",
      "version": "0.17.0",
      "fingerprint": "ba8429a39e537cb86305b4438d0293c04ff7f286fd7a403cf20a232ba2599c7e"
    },
    "timestamp": 1774020644.879564,
    "priority": 1,
    "correlation_id": "",
    "ttl_s": 900.0,
    "id": "9a39e597-0e10-482c-bcee-a692d5286ef2"
  },
  {
    "source": "steward",
    "target": "agent-research",
    "operation": "heartbeat",
    "payload": {
      "agent_id": "steward",
      "health": 0.8531644355789665,
      "timestamp": 1774020644.879558,
      "capabilities": [
        "code_analysis",
        "task_execution",
        "ci_automation",
        "federation_bridge",
        "autonomous_daemon"
      ],
      "repo": "kimeisele/steward",
      "version": "0.17.0",
      "fingerprint": "ba8429a39e537cb86305b4438d0293c04ff7f286fd7a403cf20a232ba2599c7e"
    },
    "timestamp": 1774020644.879564,
    "priority": 1,
    "correlation_id": "",
    "ttl_s": 900.0,
    "id": "e29d1292-6505-4946-aee0-a65a312f411f"
  },
  {
    "source": "steward",
    "target": "steward-gateway",
    "operation": "heartbeat",
    "payload": {
      "agent_id": "steward",
      "health": 0.8531644355789665,
      "timestamp": 1774020644.879558,
      "capabilities": [
        "code_analysis",
        "task_execution",
        "ci_automation",
        "federation_bridge",
        "autonomous_daemon"
      ],
      "repo": "kimeisele/steward",
      "version": "0.17.0",
      "fingerprint": "ba8429a39e537cb86305b4438d0293c04ff7f286fd7a403cf20a232ba2599c7e"
    },
    "timestamp": 1774020644.879564,
    "priority": 1,
    "correlation_id": "",
    "ttl_s": 900.0,
    "id": "4d54906f-fb89-4a58-93b1-3bd86546d19d"
  },
  {
    "source": "steward",
    "target": "agent-city",
    "operation": "heartbeat",
    "payload": {
      "agent_id": "steward",
      "health": 0.8574840639154846,
      "timestamp": 1774021791.4175527,
      "capabilities": [
        "code_analysis",
        "task_execution",
        "ci_automation",
        "federation_bridge",
        "autonomous_daemon"
      ],
      "repo": "kimeisele/steward",
      "version": "0.17.0",
      "fingerprint": "ba8429a39e537cb86305b4438d0293c04ff7f286fd7a403cf20a232ba2599c7e"
    },
    "timestamp": 1774021791.4176867,
    "priority": 1,
    "correlation_id": "",
    "ttl_s": 900.0,
    "id": "983a4b68-5bd1-4ef7-b955-b628531da3c4"
  },
  {
    "source": "steward",
    "target": "agent-internet",
    "operation": "heartbeat",
    "payload": {
      "agent_id": "steward",
      "health": 0.8574840639154846,
      "timestamp": 1774021791.4175527,
      "capabilities": [
        "code_analysis",
        "task_execution",
        "ci_automation",
        "federation_bridge",
        "autonomous_daemon"
      ],
      "repo": "kimeisele/steward",
      "version": "0.17.0",
      "fingerprint": "ba8429a39e537cb86305b4438d0293c04ff7f286fd7a403cf20a232ba2599c7e"
    },
    "timestamp": 1774021791.4176867,
    "priority": 1,
    "correlation_id": "",
    "ttl_s": 900.0,
    "id": "2e093542-62b5-4816-a8ff-6c248c68c050"
  },
  {
    "source": "steward",
    "target": "agent-template",
    "operation": "heartbeat",
    "payload": {
      "agent_id": "steward",
      "health": 0.8574840639154846,
      "timestamp": 1774021791.4175527,
      "capabilities": [
        "code_analysis",
        "task_execution",
        "ci_automation",
        "federation_bridge",
        "autonomous_daemon"
      ],
      "repo": "kimeisele/steward",
      "version": "0.17.0",
      "fingerprint": "ba8429a39e537cb86305b4438d0293c04ff7f286fd7a403cf20a232ba2599c7e"
    },
    "timestamp": 1774021791.4176867,
    "priority": 1,
    "correlation_id": "",
    "ttl_s": 900.0,
    "id": "7a0eff70-019d-42b0-b3ab-a23929f61cc5"
  },
  {
    "source": "steward",
    "target": "agent-world",
    "operation": "heartbeat",
    "payload": {
      "agent_id": "steward",
      "health": 0.8574840639154846,
      "timestamp": 1774021791.4175527,
      "capabilities": [
        "code_analysis",
        "task_execution",
        "ci_automation",
        "federation_bridge",
        "autonomous_daemon"
      ],
      "repo": "kimeisele/steward",
      "version": "0.17.0",
      "fingerprint": "ba8429a39e537cb86305b4438d0293c04ff7f286fd7a403cf20a232ba2599c7e"
    },
    "timestamp": 1774021791.4176867,
    "priority": 1,
    "correlation_id": "",
    "ttl_s": 900.0,
    "id": "ef02ac30-8319-4a10-9e2f-58efd58a0e85"
  },
  {
    "source": "steward",
    "target": "steward-federation",
    "operation": "heartbeat",
    "payload": {
      "agent_id": "steward",
      "health": 0.8574840639154846,
      "timestamp": 1774021791.4175527,
      "capabilities": [
        "code_analysis",
        "task_execution",
        "ci_automation",
        "federation_bridge",
        "autonomous_daemon"
      ],
      "repo": "kimeisele/steward",
      "version": "0.17.0",
      "fingerprint": "ba8429a39e537cb86305b4438d0293c04ff7f286fd7a403cf20a232ba2599c7e"
    },
    "timestamp": 1774021791.4176867,
    "priority": 1,
    "correlation_id": "",
    "ttl_s": 900.0,
    "id": "c8188586-7a21-41d7-951e-f021d36cc3f4"
  },
  {
    "source": "steward",
    "target": "steward-protocol",
    "operation": "heartbeat",
    "payload": {
      "agent_id": "steward",
      "health": 0.8574840639154846,
      "timestamp": 1774021791.4175527,
      "capabilities": [
        "code_analysis",
        "task_execution",
        "ci_automation",
        "federation_bridge",
        "autonomous_daemon"
      ],
      "repo": "kimeisele/steward",
      "version": "0.17.0",
      "fingerprint": "ba8429a39e537cb86305b4438d0293c04ff7f286fd7a403cf20a232ba2599c7e"
    },
    "timestamp": 1774021791.4176867,
    "priority": 1,
    "correlation_id": "",
    "ttl_s": 900.0,
    "id": "d6ea5fad-f235-4553-9e62-062951eece60"
  },
  {
    "source": "steward",
    "target": "steward-test",
    "operation": "heartbeat",
    "payload": {
      "agent_id": "steward",
      "health": 0.8574840639154846,
      "timestamp": 1774021791.4175527,
      "capabilities": [
        "code_analysis",
        "task_execution",
        "ci_automation",
        "federation_bridge",
        "autonomous_daemon"
      ],
      "repo": "kimeisele/steward",
      "version": "0.17.0",
      "fingerprint": "ba8429a39e537cb86305b4438d0293c04ff7f286fd7a403cf20a232ba2599c7e"
    },
    "timestamp": 1774021791.4176867,
    "priority": 1,
    "correlation_id": "",
    "ttl_s": 900.0,
    "id": "ee726b0f-1752-424a-ba0b-6421f469dc10"
  },
  {
    "source": "steward",
    "target": "agent-research",
    "operation": "heartbeat",
    "payload": {
      "agent_id": "steward",
      "health": 0.8574840639154846,
      "timestamp": 1774021791.4175527,
      "capabilities": [
        "code_analysis",
        "task_execution",
        "ci_automation",
        "federation_bridge",
        "autonomous_daemon"
      ],
      "repo": "kimeisele/steward",
      "version": "0.17.0",
      "fingerprint": "ba8429a39e537cb86305b4438d0293c04ff7f286fd7a403cf20a232ba2599c7e"
    },
    "timestamp": 1774021791.4176867,
    "priority": 1,
    "correlation_id": "",
    "ttl_s": 900.0,
    "id": "5058b521-5ad1-4d21-ae25-60db20fc0ecf"
  },
  {
    "source": "steward",
    "target": "steward-gateway",
    "operation": "heartbeat",
    "payload": {
      "agent_id": "steward",
      "health": 0.8574840639154846,
      "timestamp": 1774021791.4175527,
      "capabilities": [
        "code_analysis",
        "task_execution",
        "ci_automation",
        "federation_bridge",
        "autonomous_daemon"
      ],
      "repo": "kimeisele/steward",
      "version": "0.17.0",
      "fingerprint": "ba8429a39e537cb86305b4438d0293c04ff7f286fd7a403cf20a232ba2599c7e"
    },
    "timestamp": 1774021791.4176867,
    "priority": 1,
    "correlation_id": "",
    "ttl_s": 900.0,
    "id": "a3524f59-d8e6-4efa-aaaa-4615749104a3"
  },
  {
    "source": "steward",
    "target": "agent-city",
    "operation": "heartbeat",
    "payload": {
      "agent_id": "steward",
      "health": 0.8574840639154846,
      "timestamp": 1774021791.5856588,
      "capabilities": [
        "code_analysis",
        "task_execution",
        "ci_automation",
        "federation_bridge",
        "autonomous_daemon"
      ],
      "repo": "kimeisele/steward",
      "version": "0.17.0",
      "fingerprint": "ba8429a39e537cb86305b4438d0293c04ff7f286fd7a403cf20a232ba2599c7e"
    },
    "timestamp": 1774021791.585663,
    "priority": 1,
    "correlation_id": "",
    "ttl_s": 900.0,
    "id": "113974e9-141b-4dab-8e18-894e0de5d9bc"
  },
  {
    "source": "steward",
    "target": "agent-internet",
    "operation": "heartbeat",
    "payload": {
      "agent_id": "steward",
      "health": 0.8574840639154846,
      "timestamp": 1774021791.5856588,
      "capabilities": [
        "code_analysis",
        "task_execution",
        "ci_automation",
        "federation_bridge",
        "autonomous_daemon"
      ],
      "repo": "kimeisele/steward",
      "version": "0.17.0",
      "fingerprint": "ba8429a39e537cb86305b4438d0293c04ff7f286fd7a403cf20a232ba2599c7e"
    },
    "timestamp": 1774021791.585663,
    "priority": 1,
    "correlation_id": "",
    "ttl_s": 900.0,
    "id": "87c3d8f7-517f-4a84-a616-87ad62eddfa9"
  },
  {
    "source": "steward",
    "target": "agent-template",
    "operation": "heartbeat",
    "payload": {
      "agent_id": "steward",
      "health": 0.8574840639154846,
      "timestamp": 1774021791.5856588,
      "capabilities": [
        "code_analysis",
        "task_execution",
        "ci_automation",
        "federation_bridge",
        "autonomous_daemon"
      ],
      "repo": "kimeisele/steward",
      "version": "0.17.0",
      "fingerprint": "ba8429a39e537cb86305b4438d0293c04ff7f286fd7a403cf20a232ba2599c7e"
    },
    "timestamp": 1774021791.585663,
    "priority": 1,
    "correlation_id": "",
    "ttl_s": 900.0,
    "id": "97eeb794-e095-4b0f-a698-e6fa3b015191"
  },
  {
    "source": "steward",
    "target": "agent-world",
    "operation": "heartbeat",
    "payload": {
      "agent_id": "steward",
      "health": 0.8574840639154846,
      "timestamp": 1774021791.5856588,
      "capabilities": [
        "code_analysis",
        "task_execution",
        "ci_automation",
        "federation_bridge",
        "autonomous_daemon"
      ],
      "repo": "kimeisele/steward",
      "version": "0.17.0",
      "fingerprint": "ba8429a39e537cb86305b4438d0293c04ff7f286fd7a403cf20a232ba2599c7e"
    },
    "timestamp": 1774021791.585663,
    "priority": 1,
    "correlation_id": "",
    "ttl_s": 900.0,
    "id": "a3f942d7-5189-464d-8898-fd29eb6ab0c5"
  },
  {
    "source": "steward",
    "target": "steward-federation",
    "operation": "heartbeat",
    "payload": {
      "agent_id": "steward",
      "health": 0.8574840639154846,
      "timestamp": 1774021791.5856588,
      "capabilities": [
        "code_analysis",
        "task_execution",
        "ci_automation",
        "federation_bridge",
        "autonomous_daemon"
      ],
      "repo": "kimeisele/steward",
      "version": "0.17.0",
      "fingerprint": "ba8429a39e537cb86305b4438d0293c04ff7f286fd7a403cf20a232ba2599c7e"
    },
    "timestamp": 1774021791.585663,
    "priority": 1,
    "correlation_id": "",
    "ttl_s": 900.0,
    "id": "f9fa3fdb-f88d-4a4d-a7a6-1a39b6b7fa29"
  },
  {
    "source": "steward",
    "target": "steward-protocol",
    "operation": "heartbeat",
    "payload": {
      "agent_id": "steward",
      "health": 0.8574840639154846,
      "timestamp": 1774021791.5856588,
      "capabilities": [
        "code_analysis",
        "task_execution",
        "ci_automation",
        "federation_bridge",
        "autonomous_daemon"
      ],
      "repo": "kimeisele/steward",
      "version": "0.17.0",
      "fingerprint": "ba8429a39e537cb86305b4438d0293c04ff7f286fd7a403cf20a232ba2599c7e"
    },
    "timestamp": 1774021791.585663,
    "priority": 1,
    "correlation_id": "",
    "ttl_s": 900.0,
    "id": "705a7e7e-a408-4193-b7b4-ac832ce83dfc"
  },
  {
    "source": "steward",
    "target": "steward-test",
    "operation": "heartbeat",
    "payload": {
      "agent_id": "steward",
      "health": 0.8574840639154846,
      "timestamp": 1774021791.5856588,
      "capabilities": [
        "code_analysis",
        "task_execution",
        "ci_automation",
        "federation_bridge",
        "autonomous_daemon"
      ],
      "repo": "kimeisele/steward",
      "version": "0.17.0",
      "fingerprint": "ba8429a39e537cb86305b4438d0293c04ff7f286fd7a403cf20a232ba2599c7e"
    },
    "timestamp": 1774021791.585663,
    "priority": 1,
    "correlation_id": "",
    "ttl_s": 900.0,
    "id": "ed627654-fca6-407a-af7d-e2657e40bc7c"
  },
  {
    "source": "steward",
    "target": "agent-research",
    "operation": "heartbeat",
    "payload": {
      "agent_id": "steward",
      "health": 0.8574840639154846,
      "timestamp": 1774021791.5856588,
      "capabilities": [
        "code_analysis",
        "task_execution",
        "ci_automation",
        "federation_bridge",
        "autonomous_daemon"
      ],
      "repo": "kimeisele/steward",
      "version": "0.17.0",
      "fingerprint": "ba8429a39e537cb86305b4438d0293c04ff7f286fd7a403cf20a232ba2599c7e"
    },
    "timestamp": 1774021791.585663,
    "priority": 1,
    "correlation_id": "",
    "ttl_s": 900.0,
    "id": "4aacad3e-65b3-4f29-882a-bec7f5fdea3b"
  },
  {
    "source": "steward",
    "target": "steward-gateway",
    "operation": "heartbeat",
    "payload": {
      "agent_id": "steward",
      "health": 0.8574840639154846,
      "timestamp": 1774021791.5856588,
      "capabilities": [
        "code_analysis",
        "task_execution",
        "ci_automation",
        "federation_bridge",
        "autonomous_daemon"
      ],
      "repo": "kimeisele/steward",
      "version": "0.17.0",
      "fingerprint": "ba8429a39e537cb86305b4438d0293c04ff7f286fd7a403cf20a232ba2599c7e"
    },
    "timestamp": 1774021791.585663,
    "priority": 1,
    "correlation_id": "",
    "ttl_s": 900.0,
    "id": "936ff792-5fb9-47e4-a4ff-1717c23aa3fd"
  }
]